{
 "resumen": [
  {
   "delito": "HOMICIDIOS",
   "CODCOM": 1,
   "2024": 15,
   "2025": 10,
   "variacion": -33,
   "situación": "Disminución de Casos",
   "COMUNA": "COMUNA"
  },
  {
   "delito": "HURTOS",
   "CODCOM": 1,
   "2024": 1032,
   "2025": 957,
   "variacion": -7,
   "situación": "Disminución de Casos",
   "COMUNA": "COMUNA"
  },
  {
   "delito": "LESIONES",
   "CODCOM": 1,
   "2024": 1089,
   "2025": 1042,
   "variacion": -4,
   "situación": "Disminución de Casos",
   "COMUNA": "COMUNA"
  },
  {
   "delito": "OTROS ROBOS CON FUERZA",
   "CODCOM": 1,
   "2024": 60,
   "2025": 43,
   "variacion": -28,
   "situación": "Disminución de Casos",
   "COMUNA": "COMUNA"
  },
  {
   "delito": "ROBO CON INTIMIDACIÓN",
   "CODCOM": 1,
   "2024": 450,
   "2025": 256,
   "variacion": -43,
   "situación": "Disminución de Casos",
   "COMUNA": "COMUNA"
  },
  {
   "delito": "ROBO CON VIOLENCIA",
   "CODCOM": 1,
   "2024": 328,
   "2025": 241,
   "variacion": -27,
   "situación": "Disminución de Casos",
   "COMUNA": "COMUNA"
  },
  {
   "delito": "ROBO DE OBJETO DE O DESDE VEHÍCULO",
   "CODCOM": 1,
   "2024": 719,
   "2025": 499,
   "variacion": -31,
   "situación": "Disminución de Casos",
   "COMUNA": "COMUNA"
  },
  {
   "delito": "ROBO DE VEHÍCULO",
   "CODCOM": 1,
   "2024": 450,
   "2025": 550,
   "variacion": 22,
   "situación": "Aumento de Casos",
   "COMUNA": "COMUNA"
  },
  {
   "delito": "ROBO EN LUGAR HABITADO",
   "CODCOM": 1,
   "2024": 388,
   "2025": 255,
   "variacion": -34,
   "situación": "Disminución de Casos",
   "COMUNA": "COMUNA"
  },
  {
   "delito": "ROBO EN LUGAR NO HABITADO",
   "CODCOM": 1,
   "2024": 315,
   "2025": 236,
   "variacion": -25,
   "situación": "Disminución de Casos",
   "COMUNA": "COMUNA"
  },
  {
   "delito": "ROBO POR SORPRESA",
   "CODCOM": 1,
   "2024": 330,
   "2025": 248,
   "variacion": -25,
   "situación": "Disminución de Casos",
   "COMUNA": "COMUNA"
  },
  {
   "delito": "ROBO VIOLENTO DE VEHÍCULO",
   "CODCOM": 1,
   "2024": 118,
   "2025": 60,
   "variacion": -49,
   "situación": "Disminución de Casos",
   "COMUNA": "COMUNA"
  },
  {
   "delito": "VIOLACIONES",
   "CODCOM": 1,
   "2024": 27,
   "2025": 41,
   "variacion": 52,
   "situación": "Aumento de Casos",
   "COMUNA": "COMUNA"
  }
 ],
 "mensual": [
  {
   "delito": "HOMICIDIOS",
   "CODCOM": 1,
   "año": 2024,
   "mes": 1,
   "frecuencia": 1,
   "COMUNA": "COMUNA"
  },
  {
   "delito": "HOMICIDIOS",
   "CODCOM": 1,
   "año": 2024,
   "mes": 2,
   "frecuencia": 2,
   "COMUNA": "COMUNA"
  },
  {
   "delito": "HOMICIDIOS",
   "CODCOM": 1,
   "año": 2024,
   "mes": 3,
   "frecuencia": 1,
   "COMUNA": "COMUNA"
  },
  {
   "delito": "HOMICIDIOS",
   "CODCOM": 1,
   "año": 2024,
   "mes": 4,
   "frecuencia": 3,
   "COMUNA": "COMUNA"
  },
  {
   "delito": "HOMICIDIOS",
   "CODCOM": 1,
   "año": 2024,
   "mes": 5,
   "frecuencia": 2,
   "COMUNA": "COMUNA"
  },
  {
   "delito": "HOMICIDIOS",
   "CODCOM": 1,
   "año": 2024,
   "mes": 6,
   "frecuencia": 2,
   "COMUNA": "COMUNA"
  },
  {
   "delito": "HOMICIDIOS",
   "CODCOM": 1,
   "año": 2024,
   "mes": 7,
   "frecuencia": 4,
   "COMUNA": "COMUNA"
  },
  {
   "delito": "HOMICIDIOS",
   "CODCOM": 1,
   "año": 2024,
   "mes": 8,
   "frecuencia": 2,
   "COMUNA": "COMUNA"
  },
  {
   "delito": "HOMICIDIOS",
   "CODCOM": 1,
   "año": 2024,
   "mes": 9,
   "frecuencia": 2,
   "COMUNA": "COMUNA"
  },
  {
   "delito": "HOMICIDIOS",
   "CODCOM": 1,
   "año": 2024,
   "mes": 10,
   "frecuencia": 1,
   "COMUNA": "COMUNA"
  },
  {
   "delito": "HOMICIDIOS",
   "CODCOM": 1,
   "año": 2024,
   "mes": 11,
   "frecuencia": 1,
   "COMUNA": "COMUNA"
  },
  {
   "delito": "HOMICIDIOS",
   "CODCOM": 1,
   "año": 2024,
   "mes": 12,
   "frecuencia": 2,
   "COMUNA": "COMUNA"
  },
  {
   "delito": "HOMICIDIOS",
   "CODCOM": 1,
   "año": 2025,
   "mes": 1,
   "frecuencia": 2,
   "COMUNA": "COMUNA"
  },
  {
   "delito": "HOMICIDIOS",
   "CODCOM": 1,
   "año": 2025,
   "mes": 2,
   "frecuencia": 0,
   "COMUNA": "COMUNA"
  },
  {
   "delito": "HOMICIDIOS",
   "CODCOM": 1,
   "año": 2025,
   "mes": 3,
   "frecuencia": 0,
   "COMUNA": "COMUNA"
  },
  {
   "delito": "HOMICIDIOS",
   "CODCOM": 1,
   "año": 2025,
   "mes": 4,
   "frecuencia": 4,
   "COMUNA": "COMUNA"
  },
  {
   "delito": "HOMICIDIOS",
   "CODCOM": 1,
   "año": 2025,
   "mes": 5,
   "frecuencia": 2,
   "COMUNA": "COMUNA"
  },
  {
   "delito": "HOMICIDIOS",
   "CODCOM": 1,
   "año": 2025,
   "mes": 6,
   "frecuencia": 0,
   "COMUNA": "COMUNA"
  },
  {
   "delito": "HOMICIDIOS",
   "CODCOM": 1,
   "año": 2025,
   "mes": 7,
   "frecuencia": 1,
   "COMUNA": "COMUNA"
  },
  {
   "delito": "HOMICIDIOS",
   "CODCOM": 1,
   "año": 2025,
   "mes": 8,
   "frecuencia": 1,
   "COMUNA": "COMUNA"
  },
  {
   "delito": "HURTOS",
   "CODCOM": 1,
   "año": 2024,
   "mes": 1,
   "frecuencia": 136,
   "COMUNA": "COMUNA"
  },
  {
   "delito": "HURTOS",
   "CODCOM": 1,
   "año": 2024,
   "mes": 2,
   "frecuencia": 121,
   "COMUNA": "COMUNA"
  },
  {
   "delito": "HURTOS",
   "CODCOM": 1,
   "año": 2024,
   "mes": 3,
   "frecuencia": 144,
   "COMUNA": "COMUNA"
  },
  {
   "delito": "HURTOS",
   "CODCOM": 1,
   "año": 2024,
   "mes": 4,
   "frecuencia": 151,
   "COMUNA": "COMUNA"
  },
  {
   "delito": "HURTOS",
   "CODCOM": 1,
   "año": 2024,
   "mes": 5,
   "frecuencia": 132,
   "COMUNA": "COMUNA"
  },
  {
   "delito": "HURTOS",
   "CODCOM": 1,
   "año": 2024,
   "mes": 6,
   "frecuencia": 111,
   "COMUNA": "COMUNA"
  },
  {
   "delito": "HURTOS",
   "CODCOM": 1,
   "año": 2024,
   "mes": 7,
   "frecuencia": 189,
   "COMUNA": "COMUNA"
  },
  {
   "delito": "HURTOS",
   "CODCOM": 1,
   "año": 2024,
   "mes": 8,
   "frecuencia": 133,
   "COMUNA": "COMUNA"
  },
  {
   "delito": "HURTOS",
   "CODCOM": 1,
   "año": 2024,
   "mes": 9,
   "frecuencia": 151,
   "COMUNA": "COMUNA"
  },
  {
   "delito": "HURTOS",
   "CODCOM": 1,
   "año": 2024,
   "mes": 10,
   "frecuencia": 93,
   "COMUNA": "COMUNA"
  },
  {
   "delito": "HURTOS",
   "CODCOM": 1,
   "año": 2024,
   "mes": 11,
   "frecuencia": 115,
   "COMUNA": "COMUNA"
  },
  {
   "delito": "HURTOS",
   "CODCOM": 1,
   "año": 2024,
   "mes": 12,
   "frecuencia": 134,
   "COMUNA": "COMUNA"
  },
  {
   "delito": "HURTOS",
   "CODCOM": 1,
   "año": 2025,
   "mes": 1,
   "frecuencia": 154,
   "COMUNA": "COMUNA"
  },
  {
   "delito": "HURTOS",
   "CODCOM": 1,
   "año": 2025,
   "mes": 2,
   "frecuencia": 126,
   "COMUNA": "COMUNA"
  },
  {
   "delito": "HURTOS",
   "CODCOM": 1,
   "año": 2025,
   "mes": 3,
   "frecuencia": 115,
   "COMUNA": "COMUNA"
  },
  {
   "delito": "HURTOS",
   "CODCOM": 1,
   "año": 2025,
   "mes": 4,
   "frecuencia": 117,
   "COMUNA": "COMUNA"
  },
  {
   "delito": "HURTOS",
   "CODCOM": 1,
   "año": 2025,
   "mes": 5,
   "frecuencia": 121,
   "COMUNA": "COMUNA"
  },
  {
   "delito": "HURTOS",
   "CODCOM": 1,
   "año": 2025,
   "mes": 6,
   "frecuencia": 137,
   "COMUNA": "COMUNA"
  },
  {
   "delito": "HURTOS",
   "CODCOM": 1,
   "año": 2025,
   "mes": 7,
   "frecuencia": 159,
   "COMUNA": "COMUNA"
  },
  {
   "delito": "HURTOS",
   "CODCOM": 1,
   "año": 2025,
   "mes": 8,
   "frecuencia": 28,
   "COMUNA": "COMUNA"
  },
  {
   "delito": "LESIONES",
   "CODCOM": 1,
   "año": 2024,
   "mes": 1,
   "frecuencia": 157,
   "COMUNA": "COMUNA"
  },
  {
   "delito": "LESIONES",
   "CODCOM": 1,
   "año": 2024,
   "mes": 2,
   "frecuencia": 129,
   "COMUNA": "COMUNA"
  },
  {
   "delito": "LESIONES",
   "CODCOM": 1,
   "año": 2024,
   "mes": 3,
   "frecuencia": 160,
   "COMUNA": "COMUNA"
  },
  {
   "delito": "LESIONES",
   "CODCOM": 1,
   "año": 2024,
   "mes": 4,
   "frecuencia": 175,
   "COMUNA": "COMUNA"
  },
  {
   "delito": "LESIONES",
   "CODCOM": 1,
   "año": 2024,
   "mes": 5,
   "frecuencia": 141,
   "COMUNA": "COMUNA"
  },
  {
   "delito": "LESIONES",
   "CODCOM": 1,
   "año": 2024,
   "mes": 6,
   "frecuencia": 148,
   "COMUNA": "COMUNA"
  },
  {
   "delito": "LESIONES",
   "CODCOM": 1,
   "año": 2024,
   "mes": 7,
   "frecuencia": 157,
   "COMUNA": "COMUNA"
  },
  {
   "delito": "LESIONES",
   "CODCOM": 1,
   "año": 2024,
   "mes": 8,
   "frecuencia": 139,
   "COMUNA": "COMUNA"
  },
  {
   "delito": "LESIONES",
   "CODCOM": 1,
   "año": 2024,
   "mes": 9,
   "frecuencia": 204,
   "COMUNA": "COMUNA"
  },
  {
   "delito": "LESIONES",
   "CODCOM": 1,
   "año": 2024,
   "mes": 10,
   "frecuencia": 153,
   "COMUNA": "COMUNA"
  },
  {
   "delito": "LESIONES",
   "CODCOM": 1,
   "año": 2024,
   "mes": 11,
   "frecuencia": 148,
   "COMUNA": "COMUNA"
  },
  {
   "delito": "LESIONES",
   "CODCOM": 1,
   "año": 2024,
   "mes": 12,
   "frecuencia": 107,
   "COMUNA": "COMUNA"
  },
  {
   "delito": "LESIONES",
   "CODCOM": 1,
   "año": 2025,
   "mes": 1,
   "frecuencia": 144,
   "COMUNA": "COMUNA"
  },
  {
   "delito": "LESIONES",
   "CODCOM": 1,
   "año": 2025,
   "mes": 2,
   "frecuencia": 112,
   "COMUNA": "COMUNA"
  },
  {
   "delito": "LESIONES",
   "CODCOM": 1,
   "año": 2025,
   "mes": 3,
   "frecuencia": 187,
   "COMUNA": "COMUNA"
  },
  {
   "delito": "LESIONES",
   "CODCOM": 1,
   "año": 2025,
   "mes": 4,
   "frecuencia": 135,
   "COMUNA": "COMUNA"
  },
  {
   "delito": "LESIONES",
   "CODCOM": 1,
   "año": 2025,
   "mes": 5,
   "frecuencia": 148,
   "COMUNA": "COMUNA"
  },
  {
   "delito": "LESIONES",
   "CODCOM": 1,
   "año": 2025,
   "mes": 6,
   "frecuencia": 154,
   "COMUNA": "COMUNA"
  },
  {
   "delito": "LESIONES",
   "CODCOM": 1,
   "año": 2025,
   "mes": 7,
   "frecuencia": 124,
   "COMUNA": "COMUNA"
  },
  {
   "delito": "LESIONES",
   "CODCOM": 1,
   "año": 2025,
   "mes": 8,
   "frecuencia": 38,
   "COMUNA": "COMUNA"
  },
  {
   "delito": "OTROS ROBOS CON FUERZA",
   "CODCOM": 1,
   "año": 2024,
   "mes": 1,
   "frecuencia": 13,
   "COMUNA": "COMUNA"
  },
  {
   "delito": "OTROS ROBOS CON FUERZA",
   "CODCOM": 1,
   "año": 2024,
   "mes": 2,
   "frecuencia": 8,
   "COMUNA": "COMUNA"
  },
  {
   "delito": "OTROS ROBOS CON FUERZA",
   "CODCOM": 1,
   "año": 2024,
   "mes": 3,
   "frecuencia": 9,
   "COMUNA": "COMUNA"
  },
  {
   "delito": "OTROS ROBOS CON FUERZA",
   "CODCOM": 1,
   "año": 2024,
   "mes": 4,
   "frecuencia": 10,
   "COMUNA": "COMUNA"
  },
  {
   "delito": "OTROS ROBOS CON FUERZA",
   "CODCOM": 1,
   "año": 2024,
   "mes": 5,
   "frecuencia": 5,
   "COMUNA": "COMUNA"
  },
  {
   "delito": "OTROS ROBOS CON FUERZA",
   "CODCOM": 1,
   "año": 2024,
   "mes": 6,
   "frecuencia": 6,
   "COMUNA": "COMUNA"
  },
  {
   "delito": "OTROS ROBOS CON FUERZA",
   "CODCOM": 1,
   "año": 2024,
   "mes": 7,
   "frecuencia": 8,
   "COMUNA": "COMUNA"
  },
  {
   "delito": "OTROS ROBOS CON FUERZA",
   "CODCOM": 1,
   "año": 2024,
   "mes": 8,
   "frecuencia": 8,
   "COMUNA": "COMUNA"
  },
  {
   "delito": "OTROS ROBOS CON FUERZA",
   "CODCOM": 1,
   "año": 2024,
   "mes": 9,
   "frecuencia": 16,
   "COMUNA": "COMUNA"
  },
  {
   "delito": "OTROS ROBOS CON FUERZA",
   "CODCOM": 1,
   "año": 2024,
   "mes": 10,
   "frecuencia": 5,
   "COMUNA": "COMUNA"
  },
  {
   "delito": "OTROS ROBOS CON FUERZA",
   "CODCOM": 1,
   "año": 2024,
   "mes": 11,
   "frecuencia": 4,
   "COMUNA": "COMUNA"
  },
  {
   "delito": "OTROS ROBOS CON FUERZA",
   "CODCOM": 1,
   "año": 2024,
   "mes": 12,
   "frecuencia": 3,
   "COMUNA": "COMUNA"
  },
  {
   "delito": "OTROS ROBOS CON FUERZA",
   "CODCOM": 1,
   "año": 2025,
   "mes": 1,
   "frecuencia": 7,
   "COMUNA": "COMUNA"
  },
  {
   "delito": "OTROS ROBOS CON FUERZA",
   "CODCOM": 1,
   "año": 2025,
   "mes": 2,
   "frecuencia": 4,
   "COMUNA": "COMUNA"
  },
  {
   "delito": "OTROS ROBOS CON FUERZA",
   "CODCOM": 1,
   "año": 2025,
   "mes": 3,
   "frecuencia": 8,
   "COMUNA": "COMUNA"
  },
  {
   "delito": "OTROS ROBOS CON FUERZA",
   "CODCOM": 1,
   "año": 2025,
   "mes": 4,
   "frecuencia": 3,
   "COMUNA": "COMUNA"
  },
  {
   "delito": "OTROS ROBOS CON FUERZA",
   "CODCOM": 1,
   "año": 2025,
   "mes": 5,
   "frecuencia": 6,
   "COMUNA": "COMUNA"
  },
  {
   "delito": "OTROS ROBOS CON FUERZA",
   "CODCOM": 1,
   "año": 2025,
   "mes": 6,
   "frecuencia": 6,
   "COMUNA": "COMUNA"
  },
  {
   "delito": "OTROS ROBOS CON FUERZA",
   "CODCOM": 1,
   "año": 2025,
   "mes": 7,
   "frecuencia": 5,
   "COMUNA": "COMUNA"
  },
  {
   "delito": "OTROS ROBOS CON FUERZA",
   "CODCOM": 1,
   "año": 2025,
   "mes": 8,
   "frecuencia": 4,
   "COMUNA": "COMUNA"
  },
  {
   "delito": "ROBO CON INTIMIDACIÓN",
   "CODCOM": 1,
   "año": 2024,
   "mes": 1,
   "frecuencia": 85,
   "COMUNA": "COMUNA"
  },
  {
   "delito": "ROBO CON INTIMIDACIÓN",
   "CODCOM": 1,
   "año": 2024,
   "mes": 2,
   "frecuencia": 61,
   "COMUNA": "COMUNA"
  },
  {
   "delito": "ROBO CON INTIMIDACIÓN",
   "CODCOM": 1,
   "año": 2024,
   "mes": 3,
   "frecuencia": 59,
   "COMUNA": "COMUNA"
  },
  {
   "delito": "ROBO CON INTIMIDACIÓN",
   "CODCOM": 1,
   "año": 2024,
   "mes": 4,
   "frecuencia": 55,
   "COMUNA": "COMUNA"
  },
  {
   "delito": "ROBO CON INTIMIDACIÓN",
   "CODCOM": 1,
   "año": 2024,
   "mes": 5,
   "frecuencia": 48,
   "COMUNA": "COMUNA"
  },
  {
   "delito": "ROBO CON INTIMIDACIÓN",
   "CODCOM": 1,
   "año": 2024,
   "mes": 6,
   "frecuencia": 63,
   "COMUNA": "COMUNA"
  },
  {
   "delito": "ROBO CON INTIMIDACIÓN",
   "CODCOM": 1,
   "año": 2024,
   "mes": 7,
   "frecuencia": 66,
   "COMUNA": "COMUNA"
  },
  {
   "delito": "ROBO CON INTIMIDACIÓN",
   "CODCOM": 1,
   "año": 2024,
   "mes": 8,
   "frecuencia": 44,
   "COMUNA": "COMUNA"
  },
  {
   "delito": "ROBO CON INTIMIDACIÓN",
   "CODCOM": 1,
   "año": 2024,
   "mes": 9,
   "frecuencia": 72,
   "COMUNA": "COMUNA"
  },
  {
   "delito": "ROBO CON INTIMIDACIÓN",
   "CODCOM": 1,
   "año": 2024,
   "mes": 10,
   "frecuencia": 51,
   "COMUNA": "COMUNA"
  },
  {
   "delito": "ROBO CON INTIMIDACIÓN",
   "CODCOM": 1,
   "año": 2024,
   "mes": 11,
   "frecuencia": 41,
   "COMUNA": "COMUNA"
  },
  {
   "delito": "ROBO CON INTIMIDACIÓN",
   "CODCOM": 1,
   "año": 2024,
   "mes": 12,
   "frecuencia": 24,
   "COMUNA": "COMUNA"
  },
  {
   "delito": "ROBO CON INTIMIDACIÓN",
   "CODCOM": 1,
   "año": 2025,
   "mes": 1,
   "frecuencia": 33,
   "COMUNA": "COMUNA"
  },
  {
   "delito": "ROBO CON INTIMIDACIÓN",
   "CODCOM": 1,
   "año": 2025,
   "mes": 2,
   "frecuencia": 40,
   "COMUNA": "COMUNA"
  },
  {
   "delito": "ROBO CON INTIMIDACIÓN",
   "CODCOM": 1,
   "año": 2025,
   "mes": 3,
   "frecuencia": 36,
   "COMUNA": "COMUNA"
  },
  {
   "delito": "ROBO CON INTIMIDACIÓN",
   "CODCOM": 1,
   "año": 2025,
   "mes": 4,
   "frecuencia": 29,
   "COMUNA": "COMUNA"
  },
  {
   "delito": "ROBO CON INTIMIDACIÓN",
   "CODCOM": 1,
   "año": 2025,
   "mes": 5,
   "frecuencia": 33,
   "COMUNA": "COMUNA"
  },
  {
   "delito": "ROBO CON INTIMIDACIÓN",
   "CODCOM": 1,
   "año": 2025,
   "mes": 6,
   "frecuencia": 23,
   "COMUNA": "COMUNA"
  },
  {
   "delito": "ROBO CON INTIMIDACIÓN",
   "CODCOM": 1,
   "año": 2025,
   "mes": 7,
   "frecuencia": 50,
   "COMUNA": "COMUNA"
  },
  {
   "delito": "ROBO CON INTIMIDACIÓN",
   "CODCOM": 1,
   "año": 2025,
   "mes": 8,
   "frecuencia": 12,
   "COMUNA": "COMUNA"
  },
  {
   "delito": "ROBO CON VIOLENCIA",
   "CODCOM": 1,
   "año": 2024,
   "mes": 1,
   "frecuencia": 62,
   "COMUNA": "COMUNA"
  },
  {
   "delito": "ROBO CON VIOLENCIA",
   "CODCOM": 1,
   "año": 2024,
   "mes": 2,
   "frecuencia": 39,
   "COMUNA": "COMUNA"
  },
  {
   "delito": "ROBO CON VIOLENCIA",
   "CODCOM": 1,
   "año": 2024,
   "mes": 3,
   "frecuencia": 40,
   "COMUNA": "COMUNA"
  },
  {
   "delito": "ROBO CON VIOLENCIA",
   "CODCOM": 1,
   "año": 2024,
   "mes": 4,
   "frecuencia": 48,
   "COMUNA": "COMUNA"
  },
  {
   "delito": "ROBO CON VIOLENCIA",
   "CODCOM": 1,
   "año": 2024,
   "mes": 5,
   "frecuencia": 55,
   "COMUNA": "COMUNA"
  },
  {
   "delito": "ROBO CON VIOLENCIA",
   "CODCOM": 1,
   "año": 2024,
   "mes": 6,
   "frecuencia": 30,
   "COMUNA": "COMUNA"
  },
  {
   "delito": "ROBO CON VIOLENCIA",
   "CODCOM": 1,
   "año": 2024,
   "mes": 7,
   "frecuencia": 45,
   "COMUNA": "COMUNA"
  },
  {
   "delito": "ROBO CON VIOLENCIA",
   "CODCOM": 1,
   "año": 2024,
   "mes": 8,
   "frecuencia": 40,
   "COMUNA": "COMUNA"
  },
  {
   "delito": "ROBO CON VIOLENCIA",
   "CODCOM": 1,
   "año": 2024,
   "mes": 9,
   "frecuencia": 51,
   "COMUNA": "COMUNA"
  },
  {
   "delito": "ROBO CON VIOLENCIA",
   "CODCOM": 1,
   "año": 2024,
   "mes": 10,
   "frecuencia": 26,
   "COMUNA": "COMUNA"
  },
  {
   "delito": "ROBO CON VIOLENCIA",
   "CODCOM": 1,
   "año": 2024,
   "mes": 11,
   "frecuencia": 32,
   "COMUNA": "COMUNA"
  },
  {
   "delito": "ROBO CON VIOLENCIA",
   "CODCOM": 1,
   "año": 2024,
   "mes": 12,
   "frecuencia": 26,
   "COMUNA": "COMUNA"
  },
  {
   "delito": "ROBO CON VIOLENCIA",
   "CODCOM": 1,
   "año": 2025,
   "mes": 1,
   "frecuencia": 49,
   "COMUNA": "COMUNA"
  },
  {
   "delito": "ROBO CON VIOLENCIA",
   "CODCOM": 1,
   "año": 2025,
   "mes": 2,
   "frecuencia": 40,
   "COMUNA": "COMUNA"
  },
  {
   "delito": "ROBO CON VIOLENCIA",
   "CODCOM": 1,
   "año": 2025,
   "mes": 3,
   "frecuencia": 38,
   "COMUNA": "COMUNA"
  },
  {
   "delito": "ROBO CON VIOLENCIA",
   "CODCOM": 1,
   "año": 2025,
   "mes": 4,
   "frecuencia": 34,
   "COMUNA": "COMUNA"
  },
  {
   "delito": "ROBO CON VIOLENCIA",
   "CODCOM": 1,
   "año": 2025,
   "mes": 5,
   "frecuencia": 21,
   "COMUNA": "COMUNA"
  },
  {
   "delito": "ROBO CON VIOLENCIA",
   "CODCOM": 1,
   "año": 2025,
   "mes": 6,
   "frecuencia": 26,
   "COMUNA": "COMUNA"
  },
  {
   "delito": "ROBO CON VIOLENCIA",
   "CODCOM": 1,
   "año": 2025,
   "mes": 7,
   "frecuencia": 29,
   "COMUNA": "COMUNA"
  },
  {
   "delito": "ROBO CON VIOLENCIA",
   "CODCOM": 1,
   "año": 2025,
   "mes": 8,
   "frecuencia": 4,
   "COMUNA": "COMUNA"
  },
  {
   "delito": "ROBO DE OBJETO DE O DESDE VEHÍCULO",
   "CODCOM": 1,
   "año": 2024,
   "mes": 1,
   "frecuencia": 81,
   "COMUNA": "COMUNA"
  },
  {
   "delito": "ROBO DE OBJETO DE O DESDE VEHÍCULO",
   "CODCOM": 1,
   "año": 2024,
   "mes": 2,
   "frecuencia": 73,
   "COMUNA": "COMUNA"
  },
  {
   "delito": "ROBO DE OBJETO DE O DESDE VEHÍCULO",
   "CODCOM": 1,
   "año": 2024,
   "mes": 3,
   "frecuencia": 91,
   "COMUNA": "COMUNA"
  },
  {
   "delito": "ROBO DE OBJETO DE O DESDE VEHÍCULO",
   "CODCOM": 1,
   "año": 2024,
   "mes": 4,
   "frecuencia": 81,
   "COMUNA": "COMUNA"
  },
  {
   "delito": "ROBO DE OBJETO DE O DESDE VEHÍCULO",
   "CODCOM": 1,
   "año": 2024,
   "mes": 5,
   "frecuencia": 120,
   "COMUNA": "COMUNA"
  },
  {
   "delito": "ROBO DE OBJETO DE O DESDE VEHÍCULO",
   "CODCOM": 1,
   "año": 2024,
   "mes": 6,
   "frecuencia": 114,
   "COMUNA": "COMUNA"
  },
  {
   "delito": "ROBO DE OBJETO DE O DESDE VEHÍCULO",
   "CODCOM": 1,
   "año": 2024,
   "mes": 7,
   "frecuencia": 134,
   "COMUNA": "COMUNA"
  },
  {
   "delito": "ROBO DE OBJETO DE O DESDE VEHÍCULO",
   "CODCOM": 1,
   "año": 2024,
   "mes": 8,
   "frecuencia": 81,
   "COMUNA": "COMUNA"
  },
  {
   "delito": "ROBO DE OBJETO DE O DESDE VEHÍCULO",
   "CODCOM": 1,
   "año": 2024,
   "mes": 9,
   "frecuencia": 94,
   "COMUNA": "COMUNA"
  },
  {
   "delito": "ROBO DE OBJETO DE O DESDE VEHÍCULO",
   "CODCOM": 1,
   "año": 2024,
   "mes": 10,
   "frecuencia": 110,
   "COMUNA": "COMUNA"
  },
  {
   "delito": "ROBO DE OBJETO DE O DESDE VEHÍCULO",
   "CODCOM": 1,
   "año": 2024,
   "mes": 11,
   "frecuencia": 96,
   "COMUNA": "COMUNA"
  },
  {
   "delito": "ROBO DE OBJETO DE O DESDE VEHÍCULO",
   "CODCOM": 1,
   "año": 2024,
   "mes": 12,
   "frecuencia": 90,
   "COMUNA": "COMUNA"
  },
  {
   "delito": "ROBO DE OBJETO DE O DESDE VEHÍCULO",
   "CODCOM": 1,
   "año": 2025,
   "mes": 1,
   "frecuencia": 101,
   "COMUNA": "COMUNA"
  },
  {
   "delito": "ROBO DE OBJETO DE O DESDE VEHÍCULO",
   "CODCOM": 1,
   "año": 2025,
   "mes": 2,
   "frecuencia": 63,
   "COMUNA": "COMUNA"
  },
  {
   "delito": "ROBO DE OBJETO DE O DESDE VEHÍCULO",
   "CODCOM": 1,
   "año": 2025,
   "mes": 3,
   "frecuencia": 79,
   "COMUNA": "COMUNA"
  },
  {
   "delito": "ROBO DE OBJETO DE O DESDE VEHÍCULO",
   "CODCOM": 1,
   "año": 2025,
   "mes": 4,
   "frecuencia": 56,
   "COMUNA": "COMUNA"
  },
  {
   "delito": "ROBO DE OBJETO DE O DESDE VEHÍCULO",
   "CODCOM": 1,
   "año": 2025,
   "mes": 5,
   "frecuencia": 66,
   "COMUNA": "COMUNA"
  },
  {
   "delito": "ROBO DE OBJETO DE O DESDE VEHÍCULO",
   "CODCOM": 1,
   "año": 2025,
   "mes": 6,
   "frecuencia": 64,
   "COMUNA": "COMUNA"
  },
  {
   "delito": "ROBO DE OBJETO DE O DESDE VEHÍCULO",
   "CODCOM": 1,
   "año": 2025,
   "mes": 7,
   "frecuencia": 56,
   "COMUNA": "COMUNA"
  },
  {
   "delito": "ROBO DE OBJETO DE O DESDE VEHÍCULO",
   "CODCOM": 1,
   "año": 2025,
   "mes": 8,
   "frecuencia": 14,
   "COMUNA": "COMUNA"
  },
  {
   "delito": "ROBO DE VEHÍCULO",
   "CODCOM": 1,
   "año": 2024,
   "mes": 1,
   "frecuencia": 91,
   "COMUNA": "COMUNA"
  },
  {
   "delito": "ROBO DE VEHÍCULO",
   "CODCOM": 1,
   "año": 2024,
   "mes": 2,
   "frecuencia": 70,
   "COMUNA": "COMUNA"
  },
  {
   "delito": "ROBO DE VEHÍCULO",
   "CODCOM": 1,
   "año": 2024,
   "mes": 3,
   "frecuencia": 55,
   "COMUNA": "COMUNA"
  },
  {
   "delito": "ROBO DE VEHÍCULO",
   "CODCOM": 1,
   "año": 2024,
   "mes": 4,
   "frecuencia": 58,
   "COMUNA": "COMUNA"
  },
  {
   "delito": "ROBO DE VEHÍCULO",
   "CODCOM": 1,
   "año": 2024,
   "mes": 5,
   "frecuencia": 49,
   "COMUNA": "COMUNA"
  },
  {
   "delito": "ROBO DE VEHÍCULO",
   "CODCOM": 1,
   "año": 2024,
   "mes": 6,
   "frecuencia": 45,
   "COMUNA": "COMUNA"
  },
  {
   "delito": "ROBO DE VEHÍCULO",
   "CODCOM": 1,
   "año": 2024,
   "mes": 7,
   "frecuencia": 66,
   "COMUNA": "COMUNA"
  },
  {
   "delito": "ROBO DE VEHÍCULO",
   "CODCOM": 1,
   "año": 2024,
   "mes": 8,
   "frecuencia": 73,
   "COMUNA": "COMUNA"
  },
  {
   "delito": "ROBO DE VEHÍCULO",
   "CODCOM": 1,
   "año": 2024,
   "mes": 9,
   "frecuencia": 84,
   "COMUNA": "COMUNA"
  },
  {
   "delito": "ROBO DE VEHÍCULO",
   "CODCOM": 1,
   "año": 2024,
   "mes": 10,
   "frecuencia": 65,
   "COMUNA": "COMUNA"
  },
  {
   "delito": "ROBO DE VEHÍCULO",
   "CODCOM": 1,
   "año": 2024,
   "mes": 11,
   "frecuencia": 94,
   "COMUNA": "COMUNA"
  },
  {
   "delito": "ROBO DE VEHÍCULO",
   "CODCOM": 1,
   "año": 2024,
   "mes": 12,
   "frecuencia": 105,
   "COMUNA": "COMUNA"
  },
  {
   "delito": "ROBO DE VEHÍCULO",
   "CODCOM": 1,
   "año": 2025,
   "mes": 1,
   "frecuencia": 92,
   "COMUNA": "COMUNA"
  },
  {
   "delito": "ROBO DE VEHÍCULO",
   "CODCOM": 1,
   "año": 2025,
   "mes": 2,
   "frecuencia": 68,
   "COMUNA": "COMUNA"
  },
  {
   "delito": "ROBO DE VEHÍCULO",
   "CODCOM": 1,
   "año": 2025,
   "mes": 3,
   "frecuencia": 84,
   "COMUNA": "COMUNA"
  },
  {
   "delito": "ROBO DE VEHÍCULO",
   "CODCOM": 1,
   "año": 2025,
   "mes": 4,
   "frecuencia": 72,
   "COMUNA": "COMUNA"
  },
  {
   "delito": "ROBO DE VEHÍCULO",
   "CODCOM": 1,
   "año": 2025,
   "mes": 5,
   "frecuencia": 65,
   "COMUNA": "COMUNA"
  },
  {
   "delito": "ROBO DE VEHÍCULO",
   "CODCOM": 1,
   "año": 2025,
   "mes": 6,
   "frecuencia": 68,
   "COMUNA": "COMUNA"
  },
  {
   "delito": "ROBO DE VEHÍCULO",
   "CODCOM": 1,
   "año": 2025,
   "mes": 7,
   "frecuencia": 83,
   "COMUNA": "COMUNA"
  },
  {
   "delito": "ROBO DE VEHÍCULO",
   "CODCOM": 1,
   "año": 2025,
   "mes": 8,
   "frecuencia": 18,
   "COMUNA": "COMUNA"
  },
  {
   "delito": "ROBO EN LUGAR HABITADO",
   "CODCOM": 1,
   "año": 2024,
   "mes": 1,
   "frecuencia": 91,
   "COMUNA": "COMUNA"
  },
  {
   "delito": "ROBO EN LUGAR HABITADO",
   "CODCOM": 1,
   "año": 2024,
   "mes": 2,
   "frecuencia": 68,
   "COMUNA": "COMUNA"
  },
  {
   "delito": "ROBO EN LUGAR HABITADO",
   "CODCOM": 1,
   "año": 2024,
   "mes": 3,
   "frecuencia": 39,
   "COMUNA": "COMUNA"
  },
  {
   "delito": "ROBO EN LUGAR HABITADO",
   "CODCOM": 1,
   "año": 2024,
   "mes": 4,
   "frecuencia": 49,
   "COMUNA": "COMUNA"
  },
  {
   "delito": "ROBO EN LUGAR HABITADO",
   "CODCOM": 1,
   "año": 2024,
   "mes": 5,
   "frecuencia": 49,
   "COMUNA": "COMUNA"
  },
  {
   "delito": "ROBO EN LUGAR HABITADO",
   "CODCOM": 1,
   "año": 2024,
   "mes": 6,
   "frecuencia": 26,
   "COMUNA": "COMUNA"
  },
  {
   "delito": "ROBO EN LUGAR HABITADO",
   "CODCOM": 1,
   "año": 2024,
   "mes": 7,
   "frecuencia": 50,
   "COMUNA": "COMUNA"
  },
  {
   "delito": "ROBO EN LUGAR HABITADO",
   "CODCOM": 1,
   "año": 2024,
   "mes": 8,
   "frecuencia": 47,
   "COMUNA": "COMUNA"
  },
  {
   "delito": "ROBO EN LUGAR HABITADO",
   "CODCOM": 1,
   "año": 2024,
   "mes": 9,
   "frecuencia": 60,
   "COMUNA": "COMUNA"
  },
  {
   "delito": "ROBO EN LUGAR HABITADO",
   "CODCOM": 1,
   "año": 2024,
   "mes": 10,
   "frecuencia": 39,
   "COMUNA": "COMUNA"
  },
  {
   "delito": "ROBO EN LUGAR HABITADO",
   "CODCOM": 1,
   "año": 2024,
   "mes": 11,
   "frecuencia": 44,
   "COMUNA": "COMUNA"
  },
  {
   "delito": "ROBO EN LUGAR HABITADO",
   "CODCOM": 1,
   "año": 2024,
   "mes": 12,
   "frecuencia": 29,
   "COMUNA": "COMUNA"
  },
  {
   "delito": "ROBO EN LUGAR HABITADO",
   "CODCOM": 1,
   "año": 2025,
   "mes": 1,
   "frecuencia": 43,
   "COMUNA": "COMUNA"
  },
  {
   "delito": "ROBO EN LUGAR HABITADO",
   "CODCOM": 1,
   "año": 2025,
   "mes": 2,
   "frecuencia": 37,
   "COMUNA": "COMUNA"
  },
  {
   "delito": "ROBO EN LUGAR HABITADO",
   "CODCOM": 1,
   "año": 2025,
   "mes": 3,
   "frecuencia": 39,
   "COMUNA": "COMUNA"
  },
  {
   "delito": "ROBO EN LUGAR HABITADO",
   "CODCOM": 1,
   "año": 2025,
   "mes": 4,
   "frecuencia": 32,
   "COMUNA": "COMUNA"
  },
  {
   "delito": "ROBO EN LUGAR HABITADO",
   "CODCOM": 1,
   "año": 2025,
   "mes": 5,
   "frecuencia": 53,
   "COMUNA": "COMUNA"
  },
  {
   "delito": "ROBO EN LUGAR HABITADO",
   "CODCOM": 1,
   "año": 2025,
   "mes": 6,
   "frecuencia": 16,
   "COMUNA": "COMUNA"
  },
  {
   "delito": "ROBO EN LUGAR HABITADO",
   "CODCOM": 1,
   "año": 2025,
   "mes": 7,
   "frecuencia": 28,
   "COMUNA": "COMUNA"
  },
  {
   "delito": "ROBO EN LUGAR HABITADO",
   "CODCOM": 1,
   "año": 2025,
   "mes": 8,
   "frecuencia": 7,
   "COMUNA": "COMUNA"
  },
  {
   "delito": "ROBO EN LUGAR NO HABITADO",
   "CODCOM": 1,
   "año": 2024,
   "mes": 1,
   "frecuencia": 42,
   "COMUNA": "COMUNA"
  },
  {
   "delito": "ROBO EN LUGAR NO HABITADO",
   "CODCOM": 1,
   "año": 2024,
   "mes": 2,
   "frecuencia": 41,
   "COMUNA": "COMUNA"
  },
  {
   "delito": "ROBO EN LUGAR NO HABITADO",
   "CODCOM": 1,
   "año": 2024,
   "mes": 3,
   "frecuencia": 38,
   "COMUNA": "COMUNA"
  },
  {
   "delito": "ROBO EN LUGAR NO HABITADO",
   "CODCOM": 1,
   "año": 2024,
   "mes": 4,
   "frecuencia": 51,
   "COMUNA": "COMUNA"
  },
  {
   "delito": "ROBO EN LUGAR NO HABITADO",
   "CODCOM": 1,
   "año": 2024,
   "mes": 5,
   "frecuencia": 44,
   "COMUNA": "COMUNA"
  },
  {
   "delito": "ROBO EN LUGAR NO HABITADO",
   "CODCOM": 1,
   "año": 2024,
   "mes": 6,
   "frecuencia": 40,
   "COMUNA": "COMUNA"
  },
  {
   "delito": "ROBO EN LUGAR NO HABITADO",
   "CODCOM": 1,
   "año": 2024,
   "mes": 7,
   "frecuencia": 51,
   "COMUNA": "COMUNA"
  },
  {
   "delito": "ROBO EN LUGAR NO HABITADO",
   "CODCOM": 1,
   "año": 2024,
   "mes": 8,
   "frecuencia": 33,
   "COMUNA": "COMUNA"
  },
  {
   "delito": "ROBO EN LUGAR NO HABITADO",
   "CODCOM": 1,
   "año": 2024,
   "mes": 9,
   "frecuencia": 42,
   "COMUNA": "COMUNA"
  },
  {
   "delito": "ROBO EN LUGAR NO HABITADO",
   "CODCOM": 1,
   "año": 2024,
   "mes": 10,
   "frecuencia": 34,
   "COMUNA": "COMUNA"
  },
  {
   "delito": "ROBO EN LUGAR NO HABITADO",
   "CODCOM": 1,
   "año": 2024,
   "mes": 11,
   "frecuencia": 27,
   "COMUNA": "COMUNA"
  },
  {
   "delito": "ROBO EN LUGAR NO HABITADO",
   "CODCOM": 1,
   "año": 2024,
   "mes": 12,
   "frecuencia": 28,
   "COMUNA": "COMUNA"
  },
  {
   "delito": "ROBO EN LUGAR NO HABITADO",
   "CODCOM": 1,
   "año": 2025,
   "mes": 1,
   "frecuencia": 39,
   "COMUNA": "COMUNA"
  },
  {
   "delito": "ROBO EN LUGAR NO HABITADO",
   "CODCOM": 1,
   "año": 2025,
   "mes": 2,
   "frecuencia": 41,
   "COMUNA": "COMUNA"
  },
  {
   "delito": "ROBO EN LUGAR NO HABITADO",
   "CODCOM": 1,
   "año": 2025,
   "mes": 3,
   "frecuencia": 38,
   "COMUNA": "COMUNA"
  },
  {
   "delito": "ROBO EN LUGAR NO HABITADO",
   "CODCOM": 1,
   "año": 2025,
   "mes": 4,
   "frecuencia": 33,
   "COMUNA": "COMUNA"
  },
  {
   "delito": "ROBO EN LUGAR NO HABITADO",
   "CODCOM": 1,
   "año": 2025,
   "mes": 5,
   "frecuencia": 25,
   "COMUNA": "COMUNA"
  },
  {
   "delito": "ROBO EN LUGAR NO HABITADO",
   "CODCOM": 1,
   "año": 2025,
   "mes": 6,
   "frecuencia": 19,
   "COMUNA": "COMUNA"
  },
  {
   "delito": "ROBO EN LUGAR NO HABITADO",
   "CODCOM": 1,
   "año": 2025,
   "mes": 7,
   "frecuencia": 34,
   "COMUNA": "COMUNA"
  },
  {
   "delito": "ROBO EN LUGAR NO HABITADO",
   "CODCOM": 1,
   "año": 2025,
   "mes": 8,
   "frecuencia": 7,
   "COMUNA": "COMUNA"
  },
  {
   "delito": "ROBO POR SORPRESA",
   "CODCOM": 1,
   "año": 2024,
   "mes": 1,
   "frecuencia": 50,
   "COMUNA": "COMUNA"
  },
  {
   "delito": "ROBO POR SORPRESA",
   "CODCOM": 1,
   "año": 2024,
   "mes": 2,
   "frecuencia": 36,
   "COMUNA": "COMUNA"
  },
  {
   "delito": "ROBO POR SORPRESA",
   "CODCOM": 1,
   "año": 2024,
   "mes": 3,
   "frecuencia": 36,
   "COMUNA": "COMUNA"
  },
  {
   "delito": "ROBO POR SORPRESA",
   "CODCOM": 1,
   "año": 2024,
   "mes": 4,
   "frecuencia": 51,
   "COMUNA": "COMUNA"
  },
  {
   "delito": "ROBO POR SORPRESA",
   "CODCOM": 1,
   "año": 2024,
   "mes": 5,
   "frecuencia": 54,
   "COMUNA": "COMUNA"
  },
  {
   "delito": "ROBO POR SORPRESA",
   "CODCOM": 1,
   "año": 2024,
   "mes": 6,
   "frecuencia": 32,
   "COMUNA": "COMUNA"
  },
  {
   "delito": "ROBO POR SORPRESA",
   "CODCOM": 1,
   "año": 2024,
   "mes": 7,
   "frecuencia": 60,
   "COMUNA": "COMUNA"
  },
  {
   "delito": "ROBO POR SORPRESA",
   "CODCOM": 1,
   "año": 2024,
   "mes": 8,
   "frecuencia": 29,
   "COMUNA": "COMUNA"
  },
  {
   "delito": "ROBO POR SORPRESA",
   "CODCOM": 1,
   "año": 2024,
   "mes": 9,
   "frecuencia": 41,
   "COMUNA": "COMUNA"
  },
  {
   "delito": "ROBO POR SORPRESA",
   "CODCOM": 1,
   "año": 2024,
   "mes": 10,
   "frecuencia": 37,
   "COMUNA": "COMUNA"
  },
  {
   "delito": "ROBO POR SORPRESA",
   "CODCOM": 1,
   "año": 2024,
   "mes": 11,
   "frecuencia": 36,
   "COMUNA": "COMUNA"
  },
  {
   "delito": "ROBO POR SORPRESA",
   "CODCOM": 1,
   "año": 2024,
   "mes": 12,
   "frecuencia": 32,
   "COMUNA": "COMUNA"
  },
  {
   "delito": "ROBO POR SORPRESA",
   "CODCOM": 1,
   "año": 2025,
   "mes": 1,
   "frecuencia": 45,
   "COMUNA": "COMUNA"
  },
  {
   "delito": "ROBO POR SORPRESA",
   "CODCOM": 1,
   "año": 2025,
   "mes": 2,
   "frecuencia": 29,
   "COMUNA": "COMUNA"
  },
  {
   "delito": "ROBO POR SORPRESA",
   "CODCOM": 1,
   "año": 2025,
   "mes": 3,
   "frecuencia": 34,
   "COMUNA": "COMUNA"
  },
  {
   "delito": "ROBO POR SORPRESA",
   "CODCOM": 1,
   "año": 2025,
   "mes": 4,
   "frecuencia": 31,
   "COMUNA": "COMUNA"
  },
  {
   "delito": "ROBO POR SORPRESA",
   "CODCOM": 1,
   "año": 2025,
   "mes": 5,
   "frecuencia": 30,
   "COMUNA": "COMUNA"
  },
  {
   "delito": "ROBO POR SORPRESA",
   "CODCOM": 1,
   "año": 2025,
   "mes": 6,
   "frecuencia": 35,
   "COMUNA": "COMUNA"
  },
  {
   "delito": "ROBO POR SORPRESA",
   "CODCOM": 1,
   "año": 2025,
   "mes": 7,
   "frecuencia": 31,
   "COMUNA": "COMUNA"
  },
  {
   "delito": "ROBO POR SORPRESA",
   "CODCOM": 1,
   "año": 2025,
   "mes": 8,
   "frecuencia": 13,
   "COMUNA": "COMUNA"
  },
  {
   "delito": "ROBO VIOLENTO DE VEHÍCULO",
   "CODCOM": 1,
   "año": 2024,
   "mes": 1,
   "frecuencia": 14,
   "COMUNA": "COMUNA"
  },
  {
   "delito": "ROBO VIOLENTO DE VEHÍCULO",
   "CODCOM": 1,
   "año": 2024,
   "mes": 2,
   "frecuencia": 18,
   "COMUNA": "COMUNA"
  },
  {
   "delito": "ROBO VIOLENTO DE VEHÍCULO",
   "CODCOM": 1,
   "año": 2024,
   "mes": 3,
   "frecuencia": 15,
   "COMUNA": "COMUNA"
  },
  {
   "delito": "ROBO VIOLENTO DE VEHÍCULO",
   "CODCOM": 1,
   "año": 2024,
   "mes": 4,
   "frecuencia": 21,
   "COMUNA": "COMUNA"
  },
  {
   "delito": "ROBO VIOLENTO DE VEHÍCULO",
   "CODCOM": 1,
   "año": 2024,
   "mes": 5,
   "frecuencia": 7,
   "COMUNA": "COMUNA"
  },
  {
   "delito": "ROBO VIOLENTO DE VEHÍCULO",
   "CODCOM": 1,
   "año": 2024,
   "mes": 6,
   "frecuencia": 16,
   "COMUNA": "COMUNA"
  },
  {
   "delito": "ROBO VIOLENTO DE VEHÍCULO",
   "CODCOM": 1,
   "año": 2024,
   "mes": 7,
   "frecuencia": 20,
   "COMUNA": "COMUNA"
  },
  {
   "delito": "ROBO VIOLENTO DE VEHÍCULO",
   "CODCOM": 1,
   "año": 2024,
   "mes": 8,
   "frecuencia": 28,
   "COMUNA": "COMUNA"
  },
  {
   "delito": "ROBO VIOLENTO DE VEHÍCULO",
   "CODCOM": 1,
   "año": 2024,
   "mes": 9,
   "frecuencia": 25,
   "COMUNA": "COMUNA"
  },
  {
   "delito": "ROBO VIOLENTO DE VEHÍCULO",
   "CODCOM": 1,
   "año": 2024,
   "mes": 10,
   "frecuencia": 10,
   "COMUNA": "COMUNA"
  },
  {
   "delito": "ROBO VIOLENTO DE VEHÍCULO",
   "CODCOM": 1,
   "año": 2024,
   "mes": 11,
   "frecuencia": 13,
   "COMUNA": "COMUNA"
  },
  {
   "delito": "ROBO VIOLENTO DE VEHÍCULO",
   "CODCOM": 1,
   "año": 2024,
   "mes": 12,
   "frecuencia": 10,
   "COMUNA": "COMUNA"
  },
  {
   "delito": "ROBO VIOLENTO DE VEHÍCULO",
   "CODCOM": 1,
   "año": 2025,
   "mes": 1,
   "frecuencia": 5,
   "COMUNA": "COMUNA"
  },
  {
   "delito": "ROBO VIOLENTO DE VEHÍCULO",
   "CODCOM": 1,
   "año": 2025,
   "mes": 2,
   "frecuencia": 10,
   "COMUNA": "COMUNA"
  },
  {
   "delito": "ROBO VIOLENTO DE VEHÍCULO",
   "CODCOM": 1,
   "año": 2025,
   "mes": 3,
   "frecuencia": 12,
   "COMUNA": "COMUNA"
  },
  {
   "delito": "ROBO VIOLENTO DE VEHÍCULO",
   "CODCOM": 1,
   "año": 2025,
   "mes": 4,
   "frecuencia": 10,
   "COMUNA": "COMUNA"
  },
  {
   "delito": "ROBO VIOLENTO DE VEHÍCULO",
   "CODCOM": 1,
   "año": 2025,
   "mes": 5,
   "frecuencia": 6,
   "COMUNA": "COMUNA"
  },
  {
   "delito": "ROBO VIOLENTO DE VEHÍCULO",
   "CODCOM": 1,
   "año": 2025,
   "mes": 6,
   "frecuencia": 8,
   "COMUNA": "COMUNA"
  },
  {
   "delito": "ROBO VIOLENTO DE VEHÍCULO",
   "CODCOM": 1,
   "año": 2025,
   "mes": 7,
   "frecuencia": 8,
   "COMUNA": "COMUNA"
  },
  {
   "delito": "ROBO VIOLENTO DE VEHÍCULO",
   "CODCOM": 1,
   "año": 2025,
   "mes": 8,
   "frecuencia": 1,
   "COMUNA": "COMUNA"
  },
  {
   "delito": "VIOLACIONES",
   "CODCOM": 1,
   "año": 2024,
   "mes": 1,
   "frecuencia": 6,
   "COMUNA": "COMUNA"
  },
  {
   "delito": "VIOLACIONES",
   "CODCOM": 1,
   "año": 2024,
   "mes": 2,
   "frecuencia": 7,
   "COMUNA": "COMUNA"
  },
  {
   "delito": "VIOLACIONES",
   "CODCOM": 1,
   "año": 2024,
   "mes": 3,
   "frecuencia": 4,
   "COMUNA": "COMUNA"
  },
  {
   "delito": "VIOLACIONES",
   "CODCOM": 1,
   "año": 2024,
   "mes": 4,
   "frecuencia": 2,
   "COMUNA": "COMUNA"
  },
  {
   "delito": "VIOLACIONES",
   "CODCOM": 1,
   "año": 2024,
   "mes": 5,
   "frecuencia": 0,
   "COMUNA": "COMUNA"
  },
  {
   "delito": "VIOLACIONES",
   "CODCOM": 1,
   "año": 2024,
   "mes": 6,
   "frecuencia": 3,
   "COMUNA": "COMUNA"
  },
  {
   "delito": "VIOLACIONES",
   "CODCOM": 1,
   "año": 2024,
   "mes": 7,
   "frecuencia": 5,
   "COMUNA": "COMUNA"
  },
  {
   "delito": "VIOLACIONES",
   "CODCOM": 1,
   "año": 2024,
   "mes": 8,
   "frecuencia": 2,
   "COMUNA": "COMUNA"
  },
  {
   "delito": "VIOLACIONES",
   "CODCOM": 1,
   "año": 2024,
   "mes": 9,
   "frecuencia": 2,
   "COMUNA": "COMUNA"
  },
  {
   "delito": "VIOLACIONES",
   "CODCOM": 1,
   "año": 2024,
   "mes": 10,
   "frecuencia": 6,
   "COMUNA": "COMUNA"
  },
  {
   "delito": "VIOLACIONES",
   "CODCOM": 1,
   "año": 2024,
   "mes": 11,
   "frecuencia": 5,
   "COMUNA": "COMUNA"
  },
  {
   "delito": "VIOLACIONES",
   "CODCOM": 1,
   "año": 2024,
   "mes": 12,
   "frecuencia": 4,
   "COMUNA": "COMUNA"
  },
  {
   "delito": "VIOLACIONES",
   "CODCOM": 1,
   "año": 2025,
   "mes": 1,
   "frecuencia": 8,
   "COMUNA": "COMUNA"
  },
  {
   "delito": "VIOLACIONES",
   "CODCOM": 1,
   "año": 2025,
   "mes": 2,
   "frecuencia": 3,
   "COMUNA": "COMUNA"
  },
  {
   "delito": "VIOLACIONES",
   "CODCOM": 1,
   "año": 2025,
   "mes": 3,
   "frecuencia": 6,
   "COMUNA": "COMUNA"
  },
  {
   "delito": "VIOLACIONES",
   "CODCOM": 1,
   "año": 2025,
   "mes": 4,
   "frecuencia": 7,
   "COMUNA": "COMUNA"
  },
  {
   "delito": "VIOLACIONES",
   "CODCOM": 1,
   "año": 2025,
   "mes": 5,
   "frecuencia": 6,
   "COMUNA": "COMUNA"
  },
  {
   "delito": "VIOLACIONES",
   "CODCOM": 1,
   "año": 2025,
   "mes": 6,
   "frecuencia": 4,
   "COMUNA": "COMUNA"
  },
  {
   "delito": "VIOLACIONES",
   "CODCOM": 1,
   "año": 2025,
   "mes": 7,
   "frecuencia": 7,
   "COMUNA": "COMUNA"
  },
  {
   "delito": "VIOLACIONES",
   "CODCOM": 1,
   "año": 2025,
   "mes": 8,
   "frecuencia": 0,
   "COMUNA": "COMUNA"
  }
 ],
 "info": [
  {
   "informacion": "Casos",
   "CODCOM": 1,
   "delito": "HOMICIDIOS",
   "2024": 15,
   "2025": 10,
   "COMUNA": "COMUNA"
  },
  {
   "informacion": "Casos",
   "CODCOM": 1,
   "delito": "HURTOS",
   "2024": 1032,
   "2025": 957,
   "COMUNA": "COMUNA"
  },
  {
   "informacion": "Casos",
   "CODCOM": 1,
   "delito": "LESIONES",
   "2024": 1089,
   "2025": 1042,
   "COMUNA": "COMUNA"
  },
  {
   "informacion": "Casos",
   "CODCOM": 1,
   "delito": "OTROS ROBOS CON FUERZA",
   "2024": 60,
   "2025": 43,
   "COMUNA": "COMUNA"
  },
  {
   "informacion": "Casos",
   "CODCOM": 1,
   "delito": "ROBO CON INTIMIDACIÓN",
   "2024": 450,
   "2025": 256,
   "COMUNA": "COMUNA"
  },
  {
   "informacion": "Casos",
   "CODCOM": 1,
   "delito": "ROBO CON VIOLENCIA",
   "2024": 328,
   "2025": 241,
   "COMUNA": "COMUNA"
  },
  {
   "informacion": "Casos",
   "CODCOM": 1,
   "delito": "ROBO DE OBJETO DE O DESDE VEHÍCULO",
   "2024": 719,
   "2025": 499,
   "COMUNA": "COMUNA"
  },
  {
   "informacion": "Casos",
   "CODCOM": 1,
   "delito": "ROBO DE VEHÍCULO",
   "2024": 450,
   "2025": 550,
   "COMUNA": "COMUNA"
  },
  {
   "informacion": "Casos",
   "CODCOM": 1,
   "delito": "ROBO EN LUGAR HABITADO",
   "2024": 388,
   "2025": 255,
   "COMUNA": "COMUNA"
  },
  {
   "informacion": "Casos",
   "CODCOM": 1,
   "delito": "ROBO EN LUGAR NO HABITADO",
   "2024": 315,
   "2025": 236,
   "COMUNA": "COMUNA"
  },
  {
   "informacion": "Casos",
   "CODCOM": 1,
   "delito": "ROBO POR SORPRESA",
   "2024": 330,
   "2025": 248,
   "COMUNA": "COMUNA"
  },
  {
   "informacion": "Casos",
   "CODCOM": 1,
   "delito": "ROBO VIOLENTO DE VEHÍCULO",
   "2024": 118,
   "2025": 60,
   "COMUNA": "COMUNA"
  },
  {
   "informacion": "Casos",
   "CODCOM": 1,
   "delito": "VIOLACIONES",
   "2024": 27,
   "2025": 41,
   "COMUNA": "COMUNA"
  },
  {
   "informacion": "Detenciones",
   "CODCOM": 1,
   "delito": "HOMICIDIOS",
   "2024": 0,
   "2025": 1,
   "COMUNA": "COMUNA"
  },
  {
   "informacion": "Detenciones",
   "CODCOM": 1,
   "delito": "HURTOS",
   "2024": 230,
   "2025": 193,
   "COMUNA": "COMUNA"
  },
  {
   "informacion": "Detenciones",
   "CODCOM": 1,
   "delito": "LESIONES",
   "2024": 316,
   "2025": 328,
   "COMUNA": "COMUNA"
  },
  {
   "informacion": "Detenciones",
   "CODCOM": 1,
   "delito": "OTROS ROBOS CON FUERZA",
   "2024": 22,
   "2025": 28,
   "COMUNA": "COMUNA"
  },
  {
   "informacion": "Detenciones",
   "CODCOM": 1,
   "delito": "ROBO CON INTIMIDACIÓN",
   "2024": 34,
   "2025": 20,
   "COMUNA": "COMUNA"
  },
  {
   "informacion": "Detenciones",
   "CODCOM": 1,
   "delito": "ROBO CON VIOLENCIA",
   "2024": 40,
   "2025": 39,
   "COMUNA": "COMUNA"
  },
  {
   "informacion": "Detenciones",
   "CODCOM": 1,
   "delito": "ROBO DE OBJETO DE O DESDE VEHÍCULO",
   "2024": 57,
   "2025": 55,
   "COMUNA": "COMUNA"
  },
  {
   "informacion": "Detenciones",
   "CODCOM": 1,
   "delito": "ROBO DE VEHÍCULO",
   "2024": 8,
   "2025": 25,
   "COMUNA": "COMUNA"
  },
  {
   "informacion": "Detenciones",
   "CODCOM": 1,
   "delito": "ROBO EN LUGAR HABITADO",
   "2024": 30,
   "2025": 28,
   "COMUNA": "COMUNA"
  },
  {
   "informacion": "Detenciones",
   "CODCOM": 1,
   "delito": "ROBO EN LUGAR NO HABITADO",
   "2024": 45,
   "2025": 36,
   "COMUNA": "COMUNA"
  },
  {
   "informacion": "Detenciones",
   "CODCOM": 1,
   "delito": "ROBO POR SORPRESA",
   "2024": 37,
   "2025": 24,
   "COMUNA": "COMUNA"
  },
  {
   "informacion": "Detenciones",
   "CODCOM": 1,
   "delito": "ROBO VIOLENTO DE VEHÍCULO",
   "2024": 12,
   "2025": 3,
   "COMUNA": "COMUNA"
  },
  {
   "informacion": "Detenciones",
   "CODCOM": 1,
   "delito": "VIOLACIONES",
   "2024": 8,
   "2025": 7,
   "COMUNA": "COMUNA"
  },
  {
   "informacion": "Detenidos",
   "CODCOM": 1,
   "delito": "HOMICIDIOS",
   "2024": 0,
   "2025": 5,
   "COMUNA": "COMUNA"
  },
  {
   "informacion": "Detenidos",
   "CODCOM": 1,
   "delito": "HURTOS",
   "2024": 267,
   "2025": 228,
   "COMUNA": "COMUNA"
  },
  {
   "informacion": "Detenidos",
   "CODCOM": 1,
   "delito": "LESIONES",
   "2024": 558,
   "2025": 580,
   "COMUNA": "COMUNA"
  },
  {
   "informacion": "Detenidos",
   "CODCOM": 1,
   "delito": "OTROS ROBOS CON FUERZA",
   "2024": 34,
   "2025": 39,
   "COMUNA": "COMUNA"
  },
  {
   "informacion": "Detenidos",
   "CODCOM": 1,
   "delito": "ROBO CON INTIMIDACIÓN",
   "2024": 53,
   "2025": 26,
   "COMUNA": "COMUNA"
  },
  {
   "informacion": "Detenidos",
   "CODCOM": 1,
   "delito": "ROBO CON VIOLENCIA",
   "2024": 68,
   "2025": 67,
   "COMUNA": "COMUNA"
  },
  {
   "informacion": "Detenidos",
   "CODCOM": 1,
   "delito": "ROBO DE OBJETO DE O DESDE VEHÍCULO",
   "2024": 69,
   "2025": 67,
   "COMUNA": "COMUNA"
  },
  {
   "informacion": "Detenidos",
   "CODCOM": 1,
   "delito": "ROBO DE VEHÍCULO",
   "2024": 14,
   "2025": 47,
   "COMUNA": "COMUNA"
  },
  {
   "informacion": "Detenidos",
   "CODCOM": 1,
   "delito": "ROBO EN LUGAR HABITADO",
   "2024": 36,
   "2025": 37,
   "COMUNA": "COMUNA"
  },
  {
   "informacion": "Detenidos",
   "CODCOM": 1,
   "delito": "ROBO EN LUGAR NO HABITADO",
   "2024": 70,
   "2025": 54,
   "COMUNA": "COMUNA"
  },
  {
   "informacion": "Detenidos",
   "CODCOM": 1,
   "delito": "ROBO POR SORPRESA",
   "2024": 41,
   "2025": 29,
   "COMUNA": "COMUNA"
  },
  {
   "informacion": "Detenidos",
   "CODCOM": 1,
   "delito": "ROBO VIOLENTO DE VEHÍCULO",
   "2024": 29,
   "2025": 4,
   "COMUNA": "COMUNA"
  },
  {
   "informacion": "Detenidos",
   "CODCOM": 1,
   "delito": "VIOLACIONES",
   "2024": 9,
   "2025": 7,
   "COMUNA": "COMUNA"
  }
 ],
 "meta": {
  "semana_id": "SEMANA 32/2025 (del 04/08/2025 al 10/08/2025)",
  "region": "Tarapacá"
 }
}