{
 "resumen": [
  {
   "delito": "HOMICIDIOS",
   "CODCOM": 1,
   "2024": 17,
   "2025": 10,
   "variacion": -41,
   "situación": "Disminución de Casos",
   "COMUNA": "NO COMUNA"
  },
  {
   "delito": "HURTOS",
   "CODCOM": 1,
   "2024": 1141,
   "2025": 1096,
   "variacion": -4,
   "situación": "Disminución de Casos",
   "COMUNA": "NO COMUNA"
  },
  {
   "delito": "LESIONES",
   "CODCOM": 1,
   "2024": 1241,
   "2025": 1169,
   "variacion": -6,
   "situación": "Disminución de Casos",
   "COMUNA": "NO COMUNA"
  },
  {
   "delito": "OTROS ROBOS CON FUERZA",
   "CODCOM": 1,
   "2024": 71,
   "2025": 52,
   "variacion": -27,
   "situación": "Disminución de Casos",
   "COMUNA": "NO COMUNA"
  },
  {
   "delito": "ROBO CON INTIMIDACIÓN",
   "CODCOM": 1,
   "2024": 496,
   "2025": 294,
   "variacion": -41,
   "situación": "Disminución de Casos",
   "COMUNA": "NO COMUNA"
  },
  {
   "delito": "ROBO CON VIOLENCIA",
   "CODCOM": 1,
   "2024": 370,
   "2025": 279,
   "variacion": -25,
   "situación": "Disminución de Casos",
   "COMUNA": "NO COMUNA"
  },
  {
   "delito": "ROBO DE OBJETO DE O DESDE VEHÍCULO",
   "CODCOM": 1,
   "2024": 790,
   "2025": 563,
   "variacion": -29,
   "situación": "Disminución de Casos",
   "COMUNA": "NO COMUNA"
  },
  {
   "delito": "ROBO DE VEHÍCULO",
   "CODCOM": 1,
   "2024": 524,
   "2025": 626,
   "variacion": 19,
   "situación": "Aumento de Casos",
   "COMUNA": "NO COMUNA"
  },
  {
   "delito": "ROBO EN LUGAR HABITADO",
   "CODCOM": 1,
   "2024": 435,
   "2025": 281,
   "variacion": -35,
   "situación": "Disminución de Casos",
   "COMUNA": "NO COMUNA"
  },
  {
   "delito": "ROBO EN LUGAR NO HABITADO",
   "CODCOM": 1,
   "2024": 348,
   "2025": 260,
   "variacion": -25,
   "situación": "Disminución de Casos",
   "COMUNA": "NO COMUNA"
  },
  {
   "delito": "ROBO POR SORPRESA",
   "CODCOM": 1,
   "2024": 357,
   "2025": 278,
   "variacion": -22,
   "situación": "Disminución de Casos",
   "COMUNA": "NO COMUNA"
  },
  {
   "delito": "ROBO VIOLENTO DE VEHÍCULO",
   "CODCOM": 1,
   "2024": 142,
   "2025": 71,
   "variacion": -50,
   "situación": "Disminución de Casos",
   "COMUNA": "NO COMUNA"
  },
  {
   "delito": "VIOLACIONES",
   "CODCOM": 1,
   "2024": 29,
   "2025": 46,
   "variacion": 59,
   "situación": "Aumento de Casos",
   "COMUNA": "NO COMUNA"
  }
 ],
 "mensual": [
  {
   "delito": "HOMICIDIOS",
   "CODCOM": 1,
   "anio": 2024,
   "mes": 1,
   "casos": 1,
   "COMUNA": "NO COMUNA"
  },
  {
   "delito": "HOMICIDIOS",
   "CODCOM": 1,
   "anio": 2024,
   "mes": 2,
   "casos": 2,
   "COMUNA": "NO COMUNA"
  },
  {
   "delito": "HOMICIDIOS",
   "CODCOM": 1,
   "anio": 2024,
   "mes": 3,
   "casos": 1,
   "COMUNA": "NO COMUNA"
  },
  {
   "delito": "HOMICIDIOS",
   "CODCOM": 1,
   "anio": 2024,
   "mes": 4,
   "casos": 3,
   "COMUNA": "NO COMUNA"
  },
  {
   "delito": "HOMICIDIOS",
   "CODCOM": 1,
   "anio": 2024,
   "mes": 5,
   "casos": 2,
   "COMUNA": "NO COMUNA"
  },
  {
   "delito": "HOMICIDIOS",
   "CODCOM": 1,
   "anio": 2024,
   "mes": 6,
   "casos": 2,
   "COMUNA": "NO COMUNA"
  },
  {
   "delito": "HOMICIDIOS",
   "CODCOM": 1,
   "anio": 2024,
   "mes": 7,
   "casos": 4,
   "COMUNA": "NO COMUNA"
  },
  {
   "delito": "HOMICIDIOS",
   "CODCOM": 1,
   "anio": 2024,
   "mes": 8,
   "casos": 2,
   "COMUNA": "NO COMUNA"
  },
  {
   "delito": "HOMICIDIOS",
   "CODCOM": 1,
   "anio": 2024,
   "mes": 9,
   "casos": 2,
   "COMUNA": "NO COMUNA"
  },
  {
   "delito": "HOMICIDIOS",
   "CODCOM": 1,
   "anio": 2024,
   "mes": 10,
   "casos": 1,
   "COMUNA": "NO COMUNA"
  },
  {
   "delito": "HOMICIDIOS",
   "CODCOM": 1,
   "anio": 2024,
   "mes": 11,
   "casos": 1,
   "COMUNA": "NO COMUNA"
  },
  {
   "delito": "HOMICIDIOS",
   "CODCOM": 1,
   "anio": 2024,
   "mes": 12,
   "casos": 2,
   "COMUNA": "NO COMUNA"
  },
  {
   "delito": "HOMICIDIOS",
   "CODCOM": 1,
   "anio": 2025,
   "mes": 1,
   "casos": 2,
   "COMUNA": "NO COMUNA"
  },
  {
   "delito": "HOMICIDIOS",
   "CODCOM": 1,
   "anio": 2025,
   "mes": 2,
   "casos": 0,
   "COMUNA": "NO COMUNA"
  },
  {
   "delito": "HOMICIDIOS",
   "CODCOM": 1,
   "anio": 2025,
   "mes": 3,
   "casos": 0,
   "COMUNA": "NO COMUNA"
  },
  {
   "delito": "HOMICIDIOS",
   "CODCOM": 1,
   "anio": 2025,
   "mes": 4,
   "casos": 4,
   "COMUNA": "NO COMUNA"
  },
  {
   "delito": "HOMICIDIOS",
   "CODCOM": 1,
   "anio": 2025,
   "mes": 5,
   "casos": 2,
   "COMUNA": "NO COMUNA"
  },
  {
   "delito": "HOMICIDIOS",
   "CODCOM": 1,
   "anio": 2025,
   "mes": 6,
   "casos": 0,
   "COMUNA": "NO COMUNA"
  },
  {
   "delito": "HOMICIDIOS",
   "CODCOM": 1,
   "anio": 2025,
   "mes": 7,
   "casos": 1,
   "COMUNA": "NO COMUNA"
  },
  {
   "delito": "HOMICIDIOS",
   "CODCOM": 1,
   "anio": 2025,
   "mes": 8,
   "casos": 1,
   "COMUNA": "NO COMUNA"
  },
  {
   "delito": "HOMICIDIOS",
   "CODCOM": 1,
   "anio": 2025,
   "mes": 9,
   "casos": 0,
   "COMUNA": "NO COMUNA"
  },
  {
   "delito": "HURTOS",
   "CODCOM": 1,
   "anio": 2024,
   "mes": 1,
   "casos": 136,
   "COMUNA": "NO COMUNA"
  },
  {
   "delito": "HURTOS",
   "CODCOM": 1,
   "anio": 2024,
   "mes": 2,
   "casos": 121,
   "COMUNA": "NO COMUNA"
  },
  {
   "delito": "HURTOS",
   "CODCOM": 1,
   "anio": 2024,
   "mes": 3,
   "casos": 144,
   "COMUNA": "NO COMUNA"
  },
  {
   "delito": "HURTOS",
   "CODCOM": 1,
   "anio": 2024,
   "mes": 4,
   "casos": 151,
   "COMUNA": "NO COMUNA"
  },
  {
   "delito": "HURTOS",
   "CODCOM": 1,
   "anio": 2024,
   "mes": 5,
   "casos": 132,
   "COMUNA": "NO COMUNA"
  },
  {
   "delito": "HURTOS",
   "CODCOM": 1,
   "anio": 2024,
   "mes": 6,
   "casos": 111,
   "COMUNA": "NO COMUNA"
  },
  {
   "delito": "HURTOS",
   "CODCOM": 1,
   "anio": 2024,
   "mes": 7,
   "casos": 189,
   "COMUNA": "NO COMUNA"
  },
  {
   "delito": "HURTOS",
   "CODCOM": 1,
   "anio": 2024,
   "mes": 8,
   "casos": 133,
   "COMUNA": "NO COMUNA"
  },
  {
   "delito": "HURTOS",
   "CODCOM": 1,
   "anio": 2024,
   "mes": 9,
   "casos": 151,
   "COMUNA": "NO COMUNA"
  },
  {
   "delito": "HURTOS",
   "CODCOM": 1,
   "anio": 2024,
   "mes": 10,
   "casos": 93,
   "COMUNA": "NO COMUNA"
  },
  {
   "delito": "HURTOS",
   "CODCOM": 1,
   "anio": 2024,
   "mes": 11,
   "casos": 115,
   "COMUNA": "NO COMUNA"
  },
  {
   "delito": "HURTOS",
   "CODCOM": 1,
   "anio": 2024,
   "mes": 12,
   "casos": 134,
   "COMUNA": "NO COMUNA"
  },
  {
   "delito": "HURTOS",
   "CODCOM": 1,
   "anio": 2025,
   "mes": 1,
   "casos": 154,
   "COMUNA": "NO COMUNA"
  },
  {
   "delito": "HURTOS",
   "CODCOM": 1,
   "anio": 2025,
   "mes": 2,
   "casos": 126,
   "COMUNA": "NO COMUNA"
  },
  {
   "delito": "HURTOS",
   "CODCOM": 1,
   "anio": 2025,
   "mes": 3,
   "casos": 115,
   "COMUNA": "NO COMUNA"
  },
  {
   "delito": "HURTOS",
   "CODCOM": 1,
   "anio": 2025,
   "mes": 4,
   "casos": 117,
   "COMUNA": "NO COMUNA"
  },
  {
   "delito": "HURTOS",
   "CODCOM": 1,
   "anio": 2025,
   "mes": 5,
   "casos": 121,
   "COMUNA": "NO COMUNA"
  },
  {
   "delito": "HURTOS",
   "CODCOM": 1,
   "anio": 2025,
   "mes": 6,
   "casos": 137,
   "COMUNA": "NO COMUNA"
  },
  {
   "delito": "HURTOS",
   "CODCOM": 1,
   "anio": 2025,
   "mes": 7,
   "casos": 159,
   "COMUNA": "NO COMUNA"
  },
  {
   "delito": "HURTOS",
   "CODCOM": 1,
   "anio": 2025,
   "mes": 8,
   "casos": 134,
   "COMUNA": "NO COMUNA"
  },
  {
   "delito": "HURTOS",
   "CODCOM": 1,
   "anio": 2025,
   "mes": 9,
   "casos": 33,
   "COMUNA": "NO COMUNA"
  },
  {
   "delito": "LESIONES",
   "CODCOM": 1,
   "anio": 2024,
   "mes": 1,
   "casos": 157,
   "COMUNA": "NO COMUNA"
  },
  {
   "delito": "LESIONES",
   "CODCOM": 1,
   "anio": 2024,
   "mes": 2,
   "casos": 129,
   "COMUNA": "NO COMUNA"
  },
  {
   "delito": "LESIONES",
   "CODCOM": 1,
   "anio": 2024,
   "mes": 3,
   "casos": 160,
   "COMUNA": "NO COMUNA"
  },
  {
   "delito": "LESIONES",
   "CODCOM": 1,
   "anio": 2024,
   "mes": 4,
   "casos": 175,
   "COMUNA": "NO COMUNA"
  },
  {
   "delito": "LESIONES",
   "CODCOM": 1,
   "anio": 2024,
   "mes": 5,
   "casos": 141,
   "COMUNA": "NO COMUNA"
  },
  {
   "delito": "LESIONES",
   "CODCOM": 1,
   "anio": 2024,
   "mes": 6,
   "casos": 148,
   "COMUNA": "NO COMUNA"
  },
  {
   "delito": "LESIONES",
   "CODCOM": 1,
   "anio": 2024,
   "mes": 7,
   "casos": 157,
   "COMUNA": "NO COMUNA"
  },
  {
   "delito": "LESIONES",
   "CODCOM": 1,
   "anio": 2024,
   "mes": 8,
   "casos": 139,
   "COMUNA": "NO COMUNA"
  },
  {
   "delito": "LESIONES",
   "CODCOM": 1,
   "anio": 2024,
   "mes": 9,
   "casos": 204,
   "COMUNA": "NO COMUNA"
  },
  {
   "delito": "LESIONES",
   "CODCOM": 1,
   "anio": 2024,
   "mes": 10,
   "casos": 153,
   "COMUNA": "NO COMUNA"
  },
  {
   "delito": "LESIONES",
   "CODCOM": 1,
   "anio": 2024,
   "mes": 11,
   "casos": 148,
   "COMUNA": "NO COMUNA"
  },
  {
   "delito": "LESIONES",
   "CODCOM": 1,
   "anio": 2024,
   "mes": 12,
   "casos": 107,
   "COMUNA": "NO COMUNA"
  },
  {
   "delito": "LESIONES",
   "CODCOM": 1,
   "anio": 2025,
   "mes": 1,
   "casos": 144,
   "COMUNA": "NO COMUNA"
  },
  {
   "delito": "LESIONES",
   "CODCOM": 1,
   "anio": 2025,
   "mes": 2,
   "casos": 112,
   "COMUNA": "NO COMUNA"
  },
  {
   "delito": "LESIONES",
   "CODCOM": 1,
   "anio": 2025,
   "mes": 3,
   "casos": 187,
   "COMUNA": "NO COMUNA"
  },
  {
   "delito": "LESIONES",
   "CODCOM": 1,
   "anio": 2025,
   "mes": 4,
   "casos": 135,
   "COMUNA": "NO COMUNA"
  },
  {
   "delito": "LESIONES",
   "CODCOM": 1,
   "anio": 2025,
   "mes": 5,
   "casos": 148,
   "COMUNA": "NO COMUNA"
  },
  {
   "delito": "LESIONES",
   "CODCOM": 1,
   "anio": 2025,
   "mes": 6,
   "casos": 154,
   "COMUNA": "NO COMUNA"
  },
  {
   "delito": "LESIONES",
   "CODCOM": 1,
   "anio": 2025,
   "mes": 7,
   "casos": 124,
   "COMUNA": "NO COMUNA"
  },
  {
   "delito": "LESIONES",
   "CODCOM": 1,
   "anio": 2025,
   "mes": 8,
   "casos": 138,
   "COMUNA": "NO COMUNA"
  },
  {
   "delito": "LESIONES",
   "CODCOM": 1,
   "anio": 2025,
   "mes": 9,
   "casos": 27,
   "COMUNA": "NO COMUNA"
  },
  {
   "delito": "OTROS ROBOS CON FUERZA",
   "CODCOM": 1,
   "anio": 2024,
   "mes": 1,
   "casos": 13,
   "COMUNA": "NO COMUNA"
  },
  {
   "delito": "OTROS ROBOS CON FUERZA",
   "CODCOM": 1,
   "anio": 2024,
   "mes": 2,
   "casos": 8,
   "COMUNA": "NO COMUNA"
  },
  {
   "delito": "OTROS ROBOS CON FUERZA",
   "CODCOM": 1,
   "anio": 2024,
   "mes": 3,
   "casos": 9,
   "COMUNA": "NO COMUNA"
  },
  {
   "delito": "OTROS ROBOS CON FUERZA",
   "CODCOM": 1,
   "anio": 2024,
   "mes": 4,
   "casos": 10,
   "COMUNA": "NO COMUNA"
  },
  {
   "delito": "OTROS ROBOS CON FUERZA",
   "CODCOM": 1,
   "anio": 2024,
   "mes": 5,
   "casos": 5,
   "COMUNA": "NO COMUNA"
  },
  {
   "delito": "OTROS ROBOS CON FUERZA",
   "CODCOM": 1,
   "anio": 2024,
   "mes": 6,
   "casos": 6,
   "COMUNA": "NO COMUNA"
  },
  {
   "delito": "OTROS ROBOS CON FUERZA",
   "CODCOM": 1,
   "anio": 2024,
   "mes": 7,
   "casos": 8,
   "COMUNA": "NO COMUNA"
  },
  {
   "delito": "OTROS ROBOS CON FUERZA",
   "CODCOM": 1,
   "anio": 2024,
   "mes": 8,
   "casos": 8,
   "COMUNA": "NO COMUNA"
  },
  {
   "delito": "OTROS ROBOS CON FUERZA",
   "CODCOM": 1,
   "anio": 2024,
   "mes": 9,
   "casos": 16,
   "COMUNA": "NO COMUNA"
  },
  {
   "delito": "OTROS ROBOS CON FUERZA",
   "CODCOM": 1,
   "anio": 2024,
   "mes": 10,
   "casos": 5,
   "COMUNA": "NO COMUNA"
  },
  {
   "delito": "OTROS ROBOS CON FUERZA",
   "CODCOM": 1,
   "anio": 2024,
   "mes": 11,
   "casos": 4,
   "COMUNA": "NO COMUNA"
  },
  {
   "delito": "OTROS ROBOS CON FUERZA",
   "CODCOM": 1,
   "anio": 2024,
   "mes": 12,
   "casos": 3,
   "COMUNA": "NO COMUNA"
  },
  {
   "delito": "OTROS ROBOS CON FUERZA",
   "CODCOM": 1,
   "anio": 2025,
   "mes": 1,
   "casos": 7,
   "COMUNA": "NO COMUNA"
  },
  {
   "delito": "OTROS ROBOS CON FUERZA",
   "CODCOM": 1,
   "anio": 2025,
   "mes": 2,
   "casos": 4,
   "COMUNA": "NO COMUNA"
  },
  {
   "delito": "OTROS ROBOS CON FUERZA",
   "CODCOM": 1,
   "anio": 2025,
   "mes": 3,
   "casos": 8,
   "COMUNA": "NO COMUNA"
  },
  {
   "delito": "OTROS ROBOS CON FUERZA",
   "CODCOM": 1,
   "anio": 2025,
   "mes": 4,
   "casos": 3,
   "COMUNA": "NO COMUNA"
  },
  {
   "delito": "OTROS ROBOS CON FUERZA",
   "CODCOM": 1,
   "anio": 2025,
   "mes": 5,
   "casos": 6,
   "COMUNA": "NO COMUNA"
  },
  {
   "delito": "OTROS ROBOS CON FUERZA",
   "CODCOM": 1,
   "anio": 2025,
   "mes": 6,
   "casos": 6,
   "COMUNA": "NO COMUNA"
  },
  {
   "delito": "OTROS ROBOS CON FUERZA",
   "CODCOM": 1,
   "anio": 2025,
   "mes": 7,
   "casos": 5,
   "COMUNA": "NO COMUNA"
  },
  {
   "delito": "OTROS ROBOS CON FUERZA",
   "CODCOM": 1,
   "anio": 2025,
   "mes": 8,
   "casos": 11,
   "COMUNA": "NO COMUNA"
  },
  {
   "delito": "OTROS ROBOS CON FUERZA",
   "CODCOM": 1,
   "anio": 2025,
   "mes": 9,
   "casos": 2,
   "COMUNA": "NO COMUNA"
  },
  {
   "delito": "ROBO CON INTIMIDACIÓN",
   "CODCOM": 1,
   "anio": 2024,
   "mes": 1,
   "casos": 85,
   "COMUNA": "NO COMUNA"
  },
  {
   "delito": "ROBO CON INTIMIDACIÓN",
   "CODCOM": 1,
   "anio": 2024,
   "mes": 2,
   "casos": 61,
   "COMUNA": "NO COMUNA"
  },
  {
   "delito": "ROBO CON INTIMIDACIÓN",
   "CODCOM": 1,
   "anio": 2024,
   "mes": 3,
   "casos": 59,
   "COMUNA": "NO COMUNA"
  },
  {
   "delito": "ROBO CON INTIMIDACIÓN",
   "CODCOM": 1,
   "anio": 2024,
   "mes": 4,
   "casos": 55,
   "COMUNA": "NO COMUNA"
  },
  {
   "delito": "ROBO CON INTIMIDACIÓN",
   "CODCOM": 1,
   "anio": 2024,
   "mes": 5,
   "casos": 48,
   "COMUNA": "NO COMUNA"
  },
  {
   "delito": "ROBO CON INTIMIDACIÓN",
   "CODCOM": 1,
   "anio": 2024,
   "mes": 6,
   "casos": 63,
   "COMUNA": "NO COMUNA"
  },
  {
   "delito": "ROBO CON INTIMIDACIÓN",
   "CODCOM": 1,
   "anio": 2024,
   "mes": 7,
   "casos": 66,
   "COMUNA": "NO COMUNA"
  },
  {
   "delito": "ROBO CON INTIMIDACIÓN",
   "CODCOM": 1,
   "anio": 2024,
   "mes": 8,
   "casos": 44,
   "COMUNA": "NO COMUNA"
  },
  {
   "delito": "ROBO CON INTIMIDACIÓN",
   "CODCOM": 1,
   "anio": 2024,
   "mes": 9,
   "casos": 72,
   "COMUNA": "NO COMUNA"
  },
  {
   "delito": "ROBO CON INTIMIDACIÓN",
   "CODCOM": 1,
   "anio": 2024,
   "mes": 10,
   "casos": 51,
   "COMUNA": "NO COMUNA"
  },
  {
   "delito": "ROBO CON INTIMIDACIÓN",
   "CODCOM": 1,
   "anio": 2024,
   "mes": 11,
   "casos": 41,
   "COMUNA": "NO COMUNA"
  },
  {
   "delito": "ROBO CON INTIMIDACIÓN",
   "CODCOM": 1,
   "anio": 2024,
   "mes": 12,
   "casos": 24,
   "COMUNA": "NO COMUNA"
  },
  {
   "delito": "ROBO CON INTIMIDACIÓN",
   "CODCOM": 1,
   "anio": 2025,
   "mes": 1,
   "casos": 33,
   "COMUNA": "NO COMUNA"
  },
  {
   "delito": "ROBO CON INTIMIDACIÓN",
   "CODCOM": 1,
   "anio": 2025,
   "mes": 2,
   "casos": 40,
   "COMUNA": "NO COMUNA"
  },
  {
   "delito": "ROBO CON INTIMIDACIÓN",
   "CODCOM": 1,
   "anio": 2025,
   "mes": 3,
   "casos": 36,
   "COMUNA": "NO COMUNA"
  },
  {
   "delito": "ROBO CON INTIMIDACIÓN",
   "CODCOM": 1,
   "anio": 2025,
   "mes": 4,
   "casos": 29,
   "COMUNA": "NO COMUNA"
  },
  {
   "delito": "ROBO CON INTIMIDACIÓN",
   "CODCOM": 1,
   "anio": 2025,
   "mes": 5,
   "casos": 33,
   "COMUNA": "NO COMUNA"
  },
  {
   "delito": "ROBO CON INTIMIDACIÓN",
   "CODCOM": 1,
   "anio": 2025,
   "mes": 6,
   "casos": 23,
   "COMUNA": "NO COMUNA"
  },
  {
   "delito": "ROBO CON INTIMIDACIÓN",
   "CODCOM": 1,
   "anio": 2025,
   "mes": 7,
   "casos": 50,
   "COMUNA": "NO COMUNA"
  },
  {
   "delito": "ROBO CON INTIMIDACIÓN",
   "CODCOM": 1,
   "anio": 2025,
   "mes": 8,
   "casos": 41,
   "COMUNA": "NO COMUNA"
  },
  {
   "delito": "ROBO CON INTIMIDACIÓN",
   "CODCOM": 1,
   "anio": 2025,
   "mes": 9,
   "casos": 9,
   "COMUNA": "NO COMUNA"
  },
  {
   "delito": "ROBO CON VIOLENCIA",
   "CODCOM": 1,
   "anio": 2024,
   "mes": 1,
   "casos": 62,
   "COMUNA": "NO COMUNA"
  },
  {
   "delito": "ROBO CON VIOLENCIA",
   "CODCOM": 1,
   "anio": 2024,
   "mes": 2,
   "casos": 39,
   "COMUNA": "NO COMUNA"
  },
  {
   "delito": "ROBO CON VIOLENCIA",
   "CODCOM": 1,
   "anio": 2024,
   "mes": 3,
   "casos": 40,
   "COMUNA": "NO COMUNA"
  },
  {
   "delito": "ROBO CON VIOLENCIA",
   "CODCOM": 1,
   "anio": 2024,
   "mes": 4,
   "casos": 48,
   "COMUNA": "NO COMUNA"
  },
  {
   "delito": "ROBO CON VIOLENCIA",
   "CODCOM": 1,
   "anio": 2024,
   "mes": 5,
   "casos": 55,
   "COMUNA": "NO COMUNA"
  },
  {
   "delito": "ROBO CON VIOLENCIA",
   "CODCOM": 1,
   "anio": 2024,
   "mes": 6,
   "casos": 30,
   "COMUNA": "NO COMUNA"
  },
  {
   "delito": "ROBO CON VIOLENCIA",
   "CODCOM": 1,
   "anio": 2024,
   "mes": 7,
   "casos": 45,
   "COMUNA": "NO COMUNA"
  },
  {
   "delito": "ROBO CON VIOLENCIA",
   "CODCOM": 1,
   "anio": 2024,
   "mes": 8,
   "casos": 40,
   "COMUNA": "NO COMUNA"
  },
  {
   "delito": "ROBO CON VIOLENCIA",
   "CODCOM": 1,
   "anio": 2024,
   "mes": 9,
   "casos": 51,
   "COMUNA": "NO COMUNA"
  },
  {
   "delito": "ROBO CON VIOLENCIA",
   "CODCOM": 1,
   "anio": 2024,
   "mes": 10,
   "casos": 26,
   "COMUNA": "NO COMUNA"
  },
  {
   "delito": "ROBO CON VIOLENCIA",
   "CODCOM": 1,
   "anio": 2024,
   "mes": 11,
   "casos": 32,
   "COMUNA": "NO COMUNA"
  },
  {
   "delito": "ROBO CON VIOLENCIA",
   "CODCOM": 1,
   "anio": 2024,
   "mes": 12,
   "casos": 26,
   "COMUNA": "NO COMUNA"
  },
  {
   "delito": "ROBO CON VIOLENCIA",
   "CODCOM": 1,
   "anio": 2025,
   "mes": 1,
   "casos": 49,
   "COMUNA": "NO COMUNA"
  },
  {
   "delito": "ROBO CON VIOLENCIA",
   "CODCOM": 1,
   "anio": 2025,
   "mes": 2,
   "casos": 40,
   "COMUNA": "NO COMUNA"
  },
  {
   "delito": "ROBO CON VIOLENCIA",
   "CODCOM": 1,
   "anio": 2025,
   "mes": 3,
   "casos": 38,
   "COMUNA": "NO COMUNA"
  },
  {
   "delito": "ROBO CON VIOLENCIA",
   "CODCOM": 1,
   "anio": 2025,
   "mes": 4,
   "casos": 34,
   "COMUNA": "NO COMUNA"
  },
  {
   "delito": "ROBO CON VIOLENCIA",
   "CODCOM": 1,
   "anio": 2025,
   "mes": 5,
   "casos": 21,
   "COMUNA": "NO COMUNA"
  },
  {
   "delito": "ROBO CON VIOLENCIA",
   "CODCOM": 1,
   "anio": 2025,
   "mes": 6,
   "casos": 26,
   "COMUNA": "NO COMUNA"
  },
  {
   "delito": "ROBO CON VIOLENCIA",
   "CODCOM": 1,
   "anio": 2025,
   "mes": 7,
   "casos": 29,
   "COMUNA": "NO COMUNA"
  },
  {
   "delito": "ROBO CON VIOLENCIA",
   "CODCOM": 1,
   "anio": 2025,
   "mes": 8,
   "casos": 31,
   "COMUNA": "NO COMUNA"
  },
  {
   "delito": "ROBO CON VIOLENCIA",
   "CODCOM": 1,
   "anio": 2025,
   "mes": 9,
   "casos": 11,
   "COMUNA": "NO COMUNA"
  },
  {
   "delito": "ROBO DE OBJETO DE O DESDE VEHÍCULO",
   "CODCOM": 1,
   "anio": 2024,
   "mes": 1,
   "casos": 81,
   "COMUNA": "NO COMUNA"
  },
  {
   "delito": "ROBO DE OBJETO DE O DESDE VEHÍCULO",
   "CODCOM": 1,
   "anio": 2024,
   "mes": 2,
   "casos": 73,
   "COMUNA": "NO COMUNA"
  },
  {
   "delito": "ROBO DE OBJETO DE O DESDE VEHÍCULO",
   "CODCOM": 1,
   "anio": 2024,
   "mes": 3,
   "casos": 91,
   "COMUNA": "NO COMUNA"
  },
  {
   "delito": "ROBO DE OBJETO DE O DESDE VEHÍCULO",
   "CODCOM": 1,
   "anio": 2024,
   "mes": 4,
   "casos": 81,
   "COMUNA": "NO COMUNA"
  },
  {
   "delito": "ROBO DE OBJETO DE O DESDE VEHÍCULO",
   "CODCOM": 1,
   "anio": 2024,
   "mes": 5,
   "casos": 120,
   "COMUNA": "NO COMUNA"
  },
  {
   "delito": "ROBO DE OBJETO DE O DESDE VEHÍCULO",
   "CODCOM": 1,
   "anio": 2024,
   "mes": 6,
   "casos": 114,
   "COMUNA": "NO COMUNA"
  },
  {
   "delito": "ROBO DE OBJETO DE O DESDE VEHÍCULO",
   "CODCOM": 1,
   "anio": 2024,
   "mes": 7,
   "casos": 134,
   "COMUNA": "NO COMUNA"
  },
  {
   "delito": "ROBO DE OBJETO DE O DESDE VEHÍCULO",
   "CODCOM": 1,
   "anio": 2024,
   "mes": 8,
   "casos": 81,
   "COMUNA": "NO COMUNA"
  },
  {
   "delito": "ROBO DE OBJETO DE O DESDE VEHÍCULO",
   "CODCOM": 1,
   "anio": 2024,
   "mes": 9,
   "casos": 94,
   "COMUNA": "NO COMUNA"
  },
  {
   "delito": "ROBO DE OBJETO DE O DESDE VEHÍCULO",
   "CODCOM": 1,
   "anio": 2024,
   "mes": 10,
   "casos": 110,
   "COMUNA": "NO COMUNA"
  },
  {
   "delito": "ROBO DE OBJETO DE O DESDE VEHÍCULO",
   "CODCOM": 1,
   "anio": 2024,
   "mes": 11,
   "casos": 96,
   "COMUNA": "NO COMUNA"
  },
  {
   "delito": "ROBO DE OBJETO DE O DESDE VEHÍCULO",
   "CODCOM": 1,
   "anio": 2024,
   "mes": 12,
   "casos": 90,
   "COMUNA": "NO COMUNA"
  },
  {
   "delito": "ROBO DE OBJETO DE O DESDE VEHÍCULO",
   "CODCOM": 1,
   "anio": 2025,
   "mes": 1,
   "casos": 101,
   "COMUNA": "NO COMUNA"
  },
  {
   "delito": "ROBO DE OBJETO DE O DESDE VEHÍCULO",
   "CODCOM": 1,
   "anio": 2025,
   "mes": 2,
   "casos": 63,
   "COMUNA": "NO COMUNA"
  },
  {
   "delito": "ROBO DE OBJETO DE O DESDE VEHÍCULO",
   "CODCOM": 1,
   "anio": 2025,
   "mes": 3,
   "casos": 79,
   "COMUNA": "NO COMUNA"
  },
  {
   "delito": "ROBO DE OBJETO DE O DESDE VEHÍCULO",
   "CODCOM": 1,
   "anio": 2025,
   "mes": 4,
   "casos": 56,
   "COMUNA": "NO COMUNA"
  },
  {
   "delito": "ROBO DE OBJETO DE O DESDE VEHÍCULO",
   "CODCOM": 1,
   "anio": 2025,
   "mes": 5,
   "casos": 66,
   "COMUNA": "NO COMUNA"
  },
  {
   "delito": "ROBO DE OBJETO DE O DESDE VEHÍCULO",
   "CODCOM": 1,
   "anio": 2025,
   "mes": 6,
   "casos": 64,
   "COMUNA": "NO COMUNA"
  },
  {
   "delito": "ROBO DE OBJETO DE O DESDE VEHÍCULO",
   "CODCOM": 1,
   "anio": 2025,
   "mes": 7,
   "casos": 56,
   "COMUNA": "NO COMUNA"
  },
  {
   "delito": "ROBO DE OBJETO DE O DESDE VEHÍCULO",
   "CODCOM": 1,
   "anio": 2025,
   "mes": 8,
   "casos": 58,
   "COMUNA": "NO COMUNA"
  },
  {
   "delito": "ROBO DE OBJETO DE O DESDE VEHÍCULO",
   "CODCOM": 1,
   "anio": 2025,
   "mes": 9,
   "casos": 20,
   "COMUNA": "NO COMUNA"
  },
  {
   "delito": "ROBO DE VEHÍCULO",
   "CODCOM": 1,
   "anio": 2024,
   "mes": 1,
   "casos": 91,
   "COMUNA": "NO COMUNA"
  },
  {
   "delito": "ROBO DE VEHÍCULO",
   "CODCOM": 1,
   "anio": 2024,
   "mes": 2,
   "casos": 70,
   "COMUNA": "NO COMUNA"
  },
  {
   "delito": "ROBO DE VEHÍCULO",
   "CODCOM": 1,
   "anio": 2024,
   "mes": 3,
   "casos": 55,
   "COMUNA": "NO COMUNA"
  },
  {
   "delito": "ROBO DE VEHÍCULO",
   "CODCOM": 1,
   "anio": 2024,
   "mes": 4,
   "casos": 58,
   "COMUNA": "NO COMUNA"
  },
  {
   "delito": "ROBO DE VEHÍCULO",
   "CODCOM": 1,
   "anio": 2024,
   "mes": 5,
   "casos": 49,
   "COMUNA": "NO COMUNA"
  },
  {
   "delito": "ROBO DE VEHÍCULO",
   "CODCOM": 1,
   "anio": 2024,
   "mes": 6,
   "casos": 45,
   "COMUNA": "NO COMUNA"
  },
  {
   "delito": "ROBO DE VEHÍCULO",
   "CODCOM": 1,
   "anio": 2024,
   "mes": 7,
   "casos": 66,
   "COMUNA": "NO COMUNA"
  },
  {
   "delito": "ROBO DE VEHÍCULO",
   "CODCOM": 1,
   "anio": 2024,
   "mes": 8,
   "casos": 73,
   "COMUNA": "NO COMUNA"
  },
  {
   "delito": "ROBO DE VEHÍCULO",
   "CODCOM": 1,
   "anio": 2024,
   "mes": 9,
   "casos": 84,
   "COMUNA": "NO COMUNA"
  },
  {
   "delito": "ROBO DE VEHÍCULO",
   "CODCOM": 1,
   "anio": 2024,
   "mes": 10,
   "casos": 65,
   "COMUNA": "NO COMUNA"
  },
  {
   "delito": "ROBO DE VEHÍCULO",
   "CODCOM": 1,
   "anio": 2024,
   "mes": 11,
   "casos": 94,
   "COMUNA": "NO COMUNA"
  },
  {
   "delito": "ROBO DE VEHÍCULO",
   "CODCOM": 1,
   "anio": 2024,
   "mes": 12,
   "casos": 105,
   "COMUNA": "NO COMUNA"
  },
  {
   "delito": "ROBO DE VEHÍCULO",
   "CODCOM": 1,
   "anio": 2025,
   "mes": 1,
   "casos": 92,
   "COMUNA": "NO COMUNA"
  },
  {
   "delito": "ROBO DE VEHÍCULO",
   "CODCOM": 1,
   "anio": 2025,
   "mes": 2,
   "casos": 68,
   "COMUNA": "NO COMUNA"
  },
  {
   "delito": "ROBO DE VEHÍCULO",
   "CODCOM": 1,
   "anio": 2025,
   "mes": 3,
   "casos": 84,
   "COMUNA": "NO COMUNA"
  },
  {
   "delito": "ROBO DE VEHÍCULO",
   "CODCOM": 1,
   "anio": 2025,
   "mes": 4,
   "casos": 72,
   "COMUNA": "NO COMUNA"
  },
  {
   "delito": "ROBO DE VEHÍCULO",
   "CODCOM": 1,
   "anio": 2025,
   "mes": 5,
   "casos": 65,
   "COMUNA": "NO COMUNA"
  },
  {
   "delito": "ROBO DE VEHÍCULO",
   "CODCOM": 1,
   "anio": 2025,
   "mes": 6,
   "casos": 68,
   "COMUNA": "NO COMUNA"
  },
  {
   "delito": "ROBO DE VEHÍCULO",
   "CODCOM": 1,
   "anio": 2025,
   "mes": 7,
   "casos": 83,
   "COMUNA": "NO COMUNA"
  },
  {
   "delito": "ROBO DE VEHÍCULO",
   "CODCOM": 1,
   "anio": 2025,
   "mes": 8,
   "casos": 76,
   "COMUNA": "NO COMUNA"
  },
  {
   "delito": "ROBO DE VEHÍCULO",
   "CODCOM": 1,
   "anio": 2025,
   "mes": 9,
   "casos": 18,
   "COMUNA": "NO COMUNA"
  },
  {
   "delito": "ROBO EN LUGAR HABITADO",
   "CODCOM": 1,
   "anio": 2024,
   "mes": 1,
   "casos": 91,
   "COMUNA": "NO COMUNA"
  },
  {
   "delito": "ROBO EN LUGAR HABITADO",
   "CODCOM": 1,
   "anio": 2024,
   "mes": 2,
   "casos": 68,
   "COMUNA": "NO COMUNA"
  },
  {
   "delito": "ROBO EN LUGAR HABITADO",
   "CODCOM": 1,
   "anio": 2024,
   "mes": 3,
   "casos": 39,
   "COMUNA": "NO COMUNA"
  },
  {
   "delito": "ROBO EN LUGAR HABITADO",
   "CODCOM": 1,
   "anio": 2024,
   "mes": 4,
   "casos": 49,
   "COMUNA": "NO COMUNA"
  },
  {
   "delito": "ROBO EN LUGAR HABITADO",
   "CODCOM": 1,
   "anio": 2024,
   "mes": 5,
   "casos": 49,
   "COMUNA": "NO COMUNA"
  },
  {
   "delito": "ROBO EN LUGAR HABITADO",
   "CODCOM": 1,
   "anio": 2024,
   "mes": 6,
   "casos": 26,
   "COMUNA": "NO COMUNA"
  },
  {
   "delito": "ROBO EN LUGAR HABITADO",
   "CODCOM": 1,
   "anio": 2024,
   "mes": 7,
   "casos": 50,
   "COMUNA": "NO COMUNA"
  },
  {
   "delito": "ROBO EN LUGAR HABITADO",
   "CODCOM": 1,
   "anio": 2024,
   "mes": 8,
   "casos": 47,
   "COMUNA": "NO COMUNA"
  },
  {
   "delito": "ROBO EN LUGAR HABITADO",
   "CODCOM": 1,
   "anio": 2024,
   "mes": 9,
   "casos": 60,
   "COMUNA": "NO COMUNA"
  },
  {
   "delito": "ROBO EN LUGAR HABITADO",
   "CODCOM": 1,
   "anio": 2024,
   "mes": 10,
   "casos": 39,
   "COMUNA": "NO COMUNA"
  },
  {
   "delito": "ROBO EN LUGAR HABITADO",
   "CODCOM": 1,
   "anio": 2024,
   "mes": 11,
   "casos": 44,
   "COMUNA": "NO COMUNA"
  },
  {
   "delito": "ROBO EN LUGAR HABITADO",
   "CODCOM": 1,
   "anio": 2024,
   "mes": 12,
   "casos": 29,
   "COMUNA": "NO COMUNA"
  },
  {
   "delito": "ROBO EN LUGAR HABITADO",
   "CODCOM": 1,
   "anio": 2025,
   "mes": 1,
   "casos": 43,
   "COMUNA": "NO COMUNA"
  },
  {
   "delito": "ROBO EN LUGAR HABITADO",
   "CODCOM": 1,
   "anio": 2025,
   "mes": 2,
   "casos": 37,
   "COMUNA": "NO COMUNA"
  },
  {
   "delito": "ROBO EN LUGAR HABITADO",
   "CODCOM": 1,
   "anio": 2025,
   "mes": 3,
   "casos": 39,
   "COMUNA": "NO COMUNA"
  },
  {
   "delito": "ROBO EN LUGAR HABITADO",
   "CODCOM": 1,
   "anio": 2025,
   "mes": 4,
   "casos": 32,
   "COMUNA": "NO COMUNA"
  },
  {
   "delito": "ROBO EN LUGAR HABITADO",
   "CODCOM": 1,
   "anio": 2025,
   "mes": 5,
   "casos": 53,
   "COMUNA": "NO COMUNA"
  },
  {
   "delito": "ROBO EN LUGAR HABITADO",
   "CODCOM": 1,
   "anio": 2025,
   "mes": 6,
   "casos": 16,
   "COMUNA": "NO COMUNA"
  },
  {
   "delito": "ROBO EN LUGAR HABITADO",
   "CODCOM": 1,
   "anio": 2025,
   "mes": 7,
   "casos": 28,
   "COMUNA": "NO COMUNA"
  },
  {
   "delito": "ROBO EN LUGAR HABITADO",
   "CODCOM": 1,
   "anio": 2025,
   "mes": 8,
   "casos": 27,
   "COMUNA": "NO COMUNA"
  },
  {
   "delito": "ROBO EN LUGAR HABITADO",
   "CODCOM": 1,
   "anio": 2025,
   "mes": 9,
   "casos": 6,
   "COMUNA": "NO COMUNA"
  },
  {
   "delito": "ROBO EN LUGAR NO HABITADO",
   "CODCOM": 1,
   "anio": 2024,
   "mes": 1,
   "casos": 42,
   "COMUNA": "NO COMUNA"
  },
  {
   "delito": "ROBO EN LUGAR NO HABITADO",
   "CODCOM": 1,
   "anio": 2024,
   "mes": 2,
   "casos": 41,
   "COMUNA": "NO COMUNA"
  },
  {
   "delito": "ROBO EN LUGAR NO HABITADO",
   "CODCOM": 1,
   "anio": 2024,
   "mes": 3,
   "casos": 38,
   "COMUNA": "NO COMUNA"
  },
  {
   "delito": "ROBO EN LUGAR NO HABITADO",
   "CODCOM": 1,
   "anio": 2024,
   "mes": 4,
   "casos": 51,
   "COMUNA": "NO COMUNA"
  },
  {
   "delito": "ROBO EN LUGAR NO HABITADO",
   "CODCOM": 1,
   "anio": 2024,
   "mes": 5,
   "casos": 44,
   "COMUNA": "NO COMUNA"
  },
  {
   "delito": "ROBO EN LUGAR NO HABITADO",
   "CODCOM": 1,
   "anio": 2024,
   "mes": 6,
   "casos": 40,
   "COMUNA": "NO COMUNA"
  },
  {
   "delito": "ROBO EN LUGAR NO HABITADO",
   "CODCOM": 1,
   "anio": 2024,
   "mes": 7,
   "casos": 51,
   "COMUNA": "NO COMUNA"
  },
  {
   "delito": "ROBO EN LUGAR NO HABITADO",
   "CODCOM": 1,
   "anio": 2024,
   "mes": 8,
   "casos": 33,
   "COMUNA": "NO COMUNA"
  },
  {
   "delito": "ROBO EN LUGAR NO HABITADO",
   "CODCOM": 1,
   "anio": 2024,
   "mes": 9,
   "casos": 42,
   "COMUNA": "NO COMUNA"
  },
  {
   "delito": "ROBO EN LUGAR NO HABITADO",
   "CODCOM": 1,
   "anio": 2024,
   "mes": 10,
   "casos": 34,
   "COMUNA": "NO COMUNA"
  },
  {
   "delito": "ROBO EN LUGAR NO HABITADO",
   "CODCOM": 1,
   "anio": 2024,
   "mes": 11,
   "casos": 27,
   "COMUNA": "NO COMUNA"
  },
  {
   "delito": "ROBO EN LUGAR NO HABITADO",
   "CODCOM": 1,
   "anio": 2024,
   "mes": 12,
   "casos": 28,
   "COMUNA": "NO COMUNA"
  },
  {
   "delito": "ROBO EN LUGAR NO HABITADO",
   "CODCOM": 1,
   "anio": 2025,
   "mes": 1,
   "casos": 39,
   "COMUNA": "NO COMUNA"
  },
  {
   "delito": "ROBO EN LUGAR NO HABITADO",
   "CODCOM": 1,
   "anio": 2025,
   "mes": 2,
   "casos": 41,
   "COMUNA": "NO COMUNA"
  },
  {
   "delito": "ROBO EN LUGAR NO HABITADO",
   "CODCOM": 1,
   "anio": 2025,
   "mes": 3,
   "casos": 38,
   "COMUNA": "NO COMUNA"
  },
  {
   "delito": "ROBO EN LUGAR NO HABITADO",
   "CODCOM": 1,
   "anio": 2025,
   "mes": 4,
   "casos": 33,
   "COMUNA": "NO COMUNA"
  },
  {
   "delito": "ROBO EN LUGAR NO HABITADO",
   "CODCOM": 1,
   "anio": 2025,
   "mes": 5,
   "casos": 25,
   "COMUNA": "NO COMUNA"
  },
  {
   "delito": "ROBO EN LUGAR NO HABITADO",
   "CODCOM": 1,
   "anio": 2025,
   "mes": 6,
   "casos": 19,
   "COMUNA": "NO COMUNA"
  },
  {
   "delito": "ROBO EN LUGAR NO HABITADO",
   "CODCOM": 1,
   "anio": 2025,
   "mes": 7,
   "casos": 34,
   "COMUNA": "NO COMUNA"
  },
  {
   "delito": "ROBO EN LUGAR NO HABITADO",
   "CODCOM": 1,
   "anio": 2025,
   "mes": 8,
   "casos": 25,
   "COMUNA": "NO COMUNA"
  },
  {
   "delito": "ROBO EN LUGAR NO HABITADO",
   "CODCOM": 1,
   "anio": 2025,
   "mes": 9,
   "casos": 6,
   "COMUNA": "NO COMUNA"
  },
  {
   "delito": "ROBO POR SORPRESA",
   "CODCOM": 1,
   "anio": 2024,
   "mes": 1,
   "casos": 50,
   "COMUNA": "NO COMUNA"
  },
  {
   "delito": "ROBO POR SORPRESA",
   "CODCOM": 1,
   "anio": 2024,
   "mes": 2,
   "casos": 36,
   "COMUNA": "NO COMUNA"
  },
  {
   "delito": "ROBO POR SORPRESA",
   "CODCOM": 1,
   "anio": 2024,
   "mes": 3,
   "casos": 36,
   "COMUNA": "NO COMUNA"
  },
  {
   "delito": "ROBO POR SORPRESA",
   "CODCOM": 1,
   "anio": 2024,
   "mes": 4,
   "casos": 51,
   "COMUNA": "NO COMUNA"
  },
  {
   "delito": "ROBO POR SORPRESA",
   "CODCOM": 1,
   "anio": 2024,
   "mes": 5,
   "casos": 54,
   "COMUNA": "NO COMUNA"
  },
  {
   "delito": "ROBO POR SORPRESA",
   "CODCOM": 1,
   "anio": 2024,
   "mes": 6,
   "casos": 32,
   "COMUNA": "NO COMUNA"
  },
  {
   "delito": "ROBO POR SORPRESA",
   "CODCOM": 1,
   "anio": 2024,
   "mes": 7,
   "casos": 60,
   "COMUNA": "NO COMUNA"
  },
  {
   "delito": "ROBO POR SORPRESA",
   "CODCOM": 1,
   "anio": 2024,
   "mes": 8,
   "casos": 29,
   "COMUNA": "NO COMUNA"
  },
  {
   "delito": "ROBO POR SORPRESA",
   "CODCOM": 1,
   "anio": 2024,
   "mes": 9,
   "casos": 41,
   "COMUNA": "NO COMUNA"
  },
  {
   "delito": "ROBO POR SORPRESA",
   "CODCOM": 1,
   "anio": 2024,
   "mes": 10,
   "casos": 37,
   "COMUNA": "NO COMUNA"
  },
  {
   "delito": "ROBO POR SORPRESA",
   "CODCOM": 1,
   "anio": 2024,
   "mes": 11,
   "casos": 36,
   "COMUNA": "NO COMUNA"
  },
  {
   "delito": "ROBO POR SORPRESA",
   "CODCOM": 1,
   "anio": 2024,
   "mes": 12,
   "casos": 32,
   "COMUNA": "NO COMUNA"
  },
  {
   "delito": "ROBO POR SORPRESA",
   "CODCOM": 1,
   "anio": 2025,
   "mes": 1,
   "casos": 45,
   "COMUNA": "NO COMUNA"
  },
  {
   "delito": "ROBO POR SORPRESA",
   "CODCOM": 1,
   "anio": 2025,
   "mes": 2,
   "casos": 29,
   "COMUNA": "NO COMUNA"
  },
  {
   "delito": "ROBO POR SORPRESA",
   "CODCOM": 1,
   "anio": 2025,
   "mes": 3,
   "casos": 34,
   "COMUNA": "NO COMUNA"
  },
  {
   "delito": "ROBO POR SORPRESA",
   "CODCOM": 1,
   "anio": 2025,
   "mes": 4,
   "casos": 31,
   "COMUNA": "NO COMUNA"
  },
  {
   "delito": "ROBO POR SORPRESA",
   "CODCOM": 1,
   "anio": 2025,
   "mes": 5,
   "casos": 30,
   "COMUNA": "NO COMUNA"
  },
  {
   "delito": "ROBO POR SORPRESA",
   "CODCOM": 1,
   "anio": 2025,
   "mes": 6,
   "casos": 35,
   "COMUNA": "NO COMUNA"
  },
  {
   "delito": "ROBO POR SORPRESA",
   "CODCOM": 1,
   "anio": 2025,
   "mes": 7,
   "casos": 31,
   "COMUNA": "NO COMUNA"
  },
  {
   "delito": "ROBO POR SORPRESA",
   "CODCOM": 1,
   "anio": 2025,
   "mes": 8,
   "casos": 33,
   "COMUNA": "NO COMUNA"
  },
  {
   "delito": "ROBO POR SORPRESA",
   "CODCOM": 1,
   "anio": 2025,
   "mes": 9,
   "casos": 10,
   "COMUNA": "NO COMUNA"
  },
  {
   "delito": "ROBO VIOLENTO DE VEHÍCULO",
   "CODCOM": 1,
   "anio": 2024,
   "mes": 1,
   "casos": 14,
   "COMUNA": "NO COMUNA"
  },
  {
   "delito": "ROBO VIOLENTO DE VEHÍCULO",
   "CODCOM": 1,
   "anio": 2024,
   "mes": 2,
   "casos": 18,
   "COMUNA": "NO COMUNA"
  },
  {
   "delito": "ROBO VIOLENTO DE VEHÍCULO",
   "CODCOM": 1,
   "anio": 2024,
   "mes": 3,
   "casos": 15,
   "COMUNA": "NO COMUNA"
  },
  {
   "delito": "ROBO VIOLENTO DE VEHÍCULO",
   "CODCOM": 1,
   "anio": 2024,
   "mes": 4,
   "casos": 21,
   "COMUNA": "NO COMUNA"
  },
  {
   "delito": "ROBO VIOLENTO DE VEHÍCULO",
   "CODCOM": 1,
   "anio": 2024,
   "mes": 5,
   "casos": 7,
   "COMUNA": "NO COMUNA"
  },
  {
   "delito": "ROBO VIOLENTO DE VEHÍCULO",
   "CODCOM": 1,
   "anio": 2024,
   "mes": 6,
   "casos": 16,
   "COMUNA": "NO COMUNA"
  },
  {
   "delito": "ROBO VIOLENTO DE VEHÍCULO",
   "CODCOM": 1,
   "anio": 2024,
   "mes": 7,
   "casos": 20,
   "COMUNA": "NO COMUNA"
  },
  {
   "delito": "ROBO VIOLENTO DE VEHÍCULO",
   "CODCOM": 1,
   "anio": 2024,
   "mes": 8,
   "casos": 28,
   "COMUNA": "NO COMUNA"
  },
  {
   "delito": "ROBO VIOLENTO DE VEHÍCULO",
   "CODCOM": 1,
   "anio": 2024,
   "mes": 9,
   "casos": 25,
   "COMUNA": "NO COMUNA"
  },
  {
   "delito": "ROBO VIOLENTO DE VEHÍCULO",
   "CODCOM": 1,
   "anio": 2024,
   "mes": 10,
   "casos": 10,
   "COMUNA": "NO COMUNA"
  },
  {
   "delito": "ROBO VIOLENTO DE VEHÍCULO",
   "CODCOM": 1,
   "anio": 2024,
   "mes": 11,
   "casos": 13,
   "COMUNA": "NO COMUNA"
  },
  {
   "delito": "ROBO VIOLENTO DE VEHÍCULO",
   "CODCOM": 1,
   "anio": 2024,
   "mes": 12,
   "casos": 10,
   "COMUNA": "NO COMUNA"
  },
  {
   "delito": "ROBO VIOLENTO DE VEHÍCULO",
   "CODCOM": 1,
   "anio": 2025,
   "mes": 1,
   "casos": 5,
   "COMUNA": "NO COMUNA"
  },
  {
   "delito": "ROBO VIOLENTO DE VEHÍCULO",
   "CODCOM": 1,
   "anio": 2025,
   "mes": 2,
   "casos": 10,
   "COMUNA": "NO COMUNA"
  },
  {
   "delito": "ROBO VIOLENTO DE VEHÍCULO",
   "CODCOM": 1,
   "anio": 2025,
   "mes": 3,
   "casos": 12,
   "COMUNA": "NO COMUNA"
  },
  {
   "delito": "ROBO VIOLENTO DE VEHÍCULO",
   "CODCOM": 1,
   "anio": 2025,
   "mes": 4,
   "casos": 10,
   "COMUNA": "NO COMUNA"
  },
  {
   "delito": "ROBO VIOLENTO DE VEHÍCULO",
   "CODCOM": 1,
   "anio": 2025,
   "mes": 5,
   "casos": 6,
   "COMUNA": "NO COMUNA"
  },
  {
   "delito": "ROBO VIOLENTO DE VEHÍCULO",
   "CODCOM": 1,
   "anio": 2025,
   "mes": 6,
   "casos": 8,
   "COMUNA": "NO COMUNA"
  },
  {
   "delito": "ROBO VIOLENTO DE VEHÍCULO",
   "CODCOM": 1,
   "anio": 2025,
   "mes": 7,
   "casos": 8,
   "COMUNA": "NO COMUNA"
  },
  {
   "delito": "ROBO VIOLENTO DE VEHÍCULO",
   "CODCOM": 1,
   "anio": 2025,
   "mes": 8,
   "casos": 6,
   "COMUNA": "NO COMUNA"
  },
  {
   "delito": "ROBO VIOLENTO DE VEHÍCULO",
   "CODCOM": 1,
   "anio": 2025,
   "mes": 9,
   "casos": 6,
   "COMUNA": "NO COMUNA"
  },
  {
   "delito": "VIOLACIONES",
   "CODCOM": 1,
   "anio": 2024,
   "mes": 1,
   "casos": 6,
   "COMUNA": "NO COMUNA"
  },
  {
   "delito": "VIOLACIONES",
   "CODCOM": 1,
   "anio": 2024,
   "mes": 2,
   "casos": 7,
   "COMUNA": "NO COMUNA"
  },
  {
   "delito": "VIOLACIONES",
   "CODCOM": 1,
   "anio": 2024,
   "mes": 3,
   "casos": 4,
   "COMUNA": "NO COMUNA"
  },
  {
   "delito": "VIOLACIONES",
   "CODCOM": 1,
   "anio": 2024,
   "mes": 4,
   "casos": 2,
   "COMUNA": "NO COMUNA"
  },
  {
   "delito": "VIOLACIONES",
   "CODCOM": 1,
   "anio": 2024,
   "mes": 5,
   "casos": 0,
   "COMUNA": "NO COMUNA"
  },
  {
   "delito": "VIOLACIONES",
   "CODCOM": 1,
   "anio": 2024,
   "mes": 6,
   "casos": 3,
   "COMUNA": "NO COMUNA"
  },
  {
   "delito": "VIOLACIONES",
   "CODCOM": 1,
   "anio": 2024,
   "mes": 7,
   "casos": 5,
   "COMUNA": "NO COMUNA"
  },
  {
   "delito": "VIOLACIONES",
   "CODCOM": 1,
   "anio": 2024,
   "mes": 8,
   "casos": 2,
   "COMUNA": "NO COMUNA"
  },
  {
   "delito": "VIOLACIONES",
   "CODCOM": 1,
   "anio": 2024,
   "mes": 9,
   "casos": 2,
   "COMUNA": "NO COMUNA"
  },
  {
   "delito": "VIOLACIONES",
   "CODCOM": 1,
   "anio": 2024,
   "mes": 10,
   "casos": 6,
   "COMUNA": "NO COMUNA"
  },
  {
   "delito": "VIOLACIONES",
   "CODCOM": 1,
   "anio": 2024,
   "mes": 11,
   "casos": 5,
   "COMUNA": "NO COMUNA"
  },
  {
   "delito": "VIOLACIONES",
   "CODCOM": 1,
   "anio": 2024,
   "mes": 12,
   "casos": 4,
   "COMUNA": "NO COMUNA"
  },
  {
   "delito": "VIOLACIONES",
   "CODCOM": 1,
   "anio": 2025,
   "mes": 1,
   "casos": 8,
   "COMUNA": "NO COMUNA"
  },
  {
   "delito": "VIOLACIONES",
   "CODCOM": 1,
   "anio": 2025,
   "mes": 2,
   "casos": 3,
   "COMUNA": "NO COMUNA"
  },
  {
   "delito": "VIOLACIONES",
   "CODCOM": 1,
   "anio": 2025,
   "mes": 3,
   "casos": 6,
   "COMUNA": "NO COMUNA"
  },
  {
   "delito": "VIOLACIONES",
   "CODCOM": 1,
   "anio": 2025,
   "mes": 4,
   "casos": 7,
   "COMUNA": "NO COMUNA"
  },
  {
   "delito": "VIOLACIONES",
   "CODCOM": 1,
   "anio": 2025,
   "mes": 5,
   "casos": 6,
   "COMUNA": "NO COMUNA"
  },
  {
   "delito": "VIOLACIONES",
   "CODCOM": 1,
   "anio": 2025,
   "mes": 6,
   "casos": 4,
   "COMUNA": "NO COMUNA"
  },
  {
   "delito": "VIOLACIONES",
   "CODCOM": 1,
   "anio": 2025,
   "mes": 7,
   "casos": 7,
   "COMUNA": "NO COMUNA"
  },
  {
   "delito": "VIOLACIONES",
   "CODCOM": 1,
   "anio": 2025,
   "mes": 8,
   "casos": 4,
   "COMUNA": "NO COMUNA"
  },
  {
   "delito": "VIOLACIONES",
   "CODCOM": 1,
   "anio": 2025,
   "mes": 9,
   "casos": 1,
   "COMUNA": "NO COMUNA"
  }
 ],
 "info": [
  {
   "informacion": "Casos",
   "CODCOM": 1,
   "delito": "HOMICIDIOS",
   "2024": 17,
   "2025": 10,
   "COMUNA": "NO COMUNA"
  },
  {
   "informacion": "Casos",
   "CODCOM": 1,
   "delito": "HURTOS",
   "2024": 1141,
   "2025": 1096,
   "COMUNA": "NO COMUNA"
  },
  {
   "informacion": "Casos",
   "CODCOM": 1,
   "delito": "LESIONES",
   "2024": 1241,
   "2025": 1169,
   "COMUNA": "NO COMUNA"
  },
  {
   "informacion": "Casos",
   "CODCOM": 1,
   "delito": "OTROS ROBOS CON FUERZA",
   "2024": 71,
   "2025": 52,
   "COMUNA": "NO COMUNA"
  },
  {
   "informacion": "Casos",
   "CODCOM": 1,
   "delito": "ROBO CON INTIMIDACIÓN",
   "2024": 496,
   "2025": 294,
   "COMUNA": "NO COMUNA"
  },
  {
   "informacion": "Casos",
   "CODCOM": 1,
   "delito": "ROBO CON VIOLENCIA",
   "2024": 370,
   "2025": 279,
   "COMUNA": "NO COMUNA"
  },
  {
   "informacion": "Casos",
   "CODCOM": 1,
   "delito": "ROBO DE OBJETO DE O DESDE VEHÍCULO",
   "2024": 790,
   "2025": 563,
   "COMUNA": "NO COMUNA"
  },
  {
   "informacion": "Casos",
   "CODCOM": 1,
   "delito": "ROBO DE VEHÍCULO",
   "2024": 524,
   "2025": 626,
   "COMUNA": "NO COMUNA"
  },
  {
   "informacion": "Casos",
   "CODCOM": 1,
   "delito": "ROBO EN LUGAR HABITADO",
   "2024": 435,
   "2025": 281,
   "COMUNA": "NO COMUNA"
  },
  {
   "informacion": "Casos",
   "CODCOM": 1,
   "delito": "ROBO EN LUGAR NO HABITADO",
   "2024": 348,
   "2025": 260,
   "COMUNA": "NO COMUNA"
  },
  {
   "informacion": "Casos",
   "CODCOM": 1,
   "delito": "ROBO POR SORPRESA",
   "2024": 357,
   "2025": 278,
   "COMUNA": "NO COMUNA"
  },
  {
   "informacion": "Casos",
   "CODCOM": 1,
   "delito": "ROBO VIOLENTO DE VEHÍCULO",
   "2024": 142,
   "2025": 71,
   "COMUNA": "NO COMUNA"
  },
  {
   "informacion": "Casos",
   "CODCOM": 1,
   "delito": "VIOLACIONES",
   "2024": 29,
   "2025": 46,
   "COMUNA": "NO COMUNA"
  },
  {
   "informacion": "Detenciones",
   "CODCOM": 1,
   "delito": "HOMICIDIOS",
   "2024": 0,
   "2025": 1,
   "COMUNA": "NO COMUNA"
  },
  {
   "informacion": "Detenciones",
   "CODCOM": 1,
   "delito": "HURTOS",
   "2024": 252,
   "2025": 236,
   "COMUNA": "NO COMUNA"
  },
  {
   "informacion": "Detenciones",
   "CODCOM": 1,
   "delito": "LESIONES",
   "2024": 350,
   "2025": 365,
   "COMUNA": "NO COMUNA"
  },
  {
   "informacion": "Detenciones",
   "CODCOM": 1,
   "delito": "OTROS ROBOS CON FUERZA",
   "2024": 33,
   "2025": 35,
   "COMUNA": "NO COMUNA"
  },
  {
   "informacion": "Detenciones",
   "CODCOM": 1,
   "delito": "ROBO CON INTIMIDACIÓN",
   "2024": 42,
   "2025": 24,
   "COMUNA": "NO COMUNA"
  },
  {
   "informacion": "Detenciones",
   "CODCOM": 1,
   "delito": "ROBO CON VIOLENCIA",
   "2024": 49,
   "2025": 45,
   "COMUNA": "NO COMUNA"
  },
  {
   "informacion": "Detenciones",
   "CODCOM": 1,
   "delito": "ROBO DE OBJETO DE O DESDE VEHÍCULO",
   "2024": 66,
   "2025": 60,
   "COMUNA": "NO COMUNA"
  },
  {
   "informacion": "Detenciones",
   "CODCOM": 1,
   "delito": "ROBO DE VEHÍCULO",
   "2024": 10,
   "2025": 30,
   "COMUNA": "NO COMUNA"
  },
  {
   "informacion": "Detenciones",
   "CODCOM": 1,
   "delito": "ROBO EN LUGAR HABITADO",
   "2024": 34,
   "2025": 31,
   "COMUNA": "NO COMUNA"
  },
  {
   "informacion": "Detenciones",
   "CODCOM": 1,
   "delito": "ROBO EN LUGAR NO HABITADO",
   "2024": 48,
   "2025": 42,
   "COMUNA": "NO COMUNA"
  },
  {
   "informacion": "Detenciones",
   "CODCOM": 1,
   "delito": "ROBO POR SORPRESA",
   "2024": 39,
   "2025": 26,
   "COMUNA": "NO COMUNA"
  },
  {
   "informacion": "Detenciones",
   "CODCOM": 1,
   "delito": "ROBO VIOLENTO DE VEHÍCULO",
   "2024": 14,
   "2025": 3,
   "COMUNA": "NO COMUNA"
  },
  {
   "informacion": "Detenciones",
   "CODCOM": 1,
   "delito": "VIOLACIONES",
   "2024": 8,
   "2025": 7,
   "COMUNA": "NO COMUNA"
  },
  {
   "informacion": "Detenidos",
   "CODCOM": 1,
   "delito": "HOMICIDIOS",
   "2024": 0,
   "2025": 5,
   "COMUNA": "NO COMUNA"
  },
  {
   "informacion": "Detenidos",
   "CODCOM": 1,
   "delito": "HURTOS",
   "2024": 292,
   "2025": 278,
   "COMUNA": "NO COMUNA"
  },
  {
   "informacion": "Detenidos",
   "CODCOM": 1,
   "delito": "LESIONES",
   "2024": 616,
   "2025": 637,
   "COMUNA": "NO COMUNA"
  },
  {
   "informacion": "Detenidos",
   "CODCOM": 1,
   "delito": "OTROS ROBOS CON FUERZA",
   "2024": 56,
   "2025": 53,
   "COMUNA": "NO COMUNA"
  },
  {
   "informacion": "Detenidos",
   "CODCOM": 1,
   "delito": "ROBO CON INTIMIDACIÓN",
   "2024": 62,
   "2025": 34,
   "COMUNA": "NO COMUNA"
  },
  {
   "informacion": "Detenidos",
   "CODCOM": 1,
   "delito": "ROBO CON VIOLENCIA",
   "2024": 87,
   "2025": 76,
   "COMUNA": "NO COMUNA"
  },
  {
   "informacion": "Detenidos",
   "CODCOM": 1,
   "delito": "ROBO DE OBJETO DE O DESDE VEHÍCULO",
   "2024": 81,
   "2025": 73,
   "COMUNA": "NO COMUNA"
  },
  {
   "informacion": "Detenidos",
   "CODCOM": 1,
   "delito": "ROBO DE VEHÍCULO",
   "2024": 17,
   "2025": 65,
   "COMUNA": "NO COMUNA"
  },
  {
   "informacion": "Detenidos",
   "CODCOM": 1,
   "delito": "ROBO EN LUGAR HABITADO",
   "2024": 41,
   "2025": 42,
   "COMUNA": "NO COMUNA"
  },
  {
   "informacion": "Detenidos",
   "CODCOM": 1,
   "delito": "ROBO EN LUGAR NO HABITADO",
   "2024": 74,
   "2025": 66,
   "COMUNA": "NO COMUNA"
  },
  {
   "informacion": "Detenidos",
   "CODCOM": 1,
   "delito": "ROBO POR SORPRESA",
   "2024": 43,
   "2025": 32,
   "COMUNA": "NO COMUNA"
  },
  {
   "informacion": "Detenidos",
   "CODCOM": 1,
   "delito": "ROBO VIOLENTO DE VEHÍCULO",
   "2024": 33,
   "2025": 4,
   "COMUNA": "NO COMUNA"
  },
  {
   "informacion": "Detenidos",
   "CODCOM": 1,
   "delito": "VIOLACIONES",
   "2024": 9,
   "2025": 7,
   "COMUNA": "NO COMUNA"
  }
 ],
 "meta": {
  "semana_id": "SEMANA 36/2025 (del 01/09/2025 al 07/09/2025)",
  "region": "Tarapacá"
 }
}