{
 "resumen": [
  {
   "delito": "HOMICIDIOS",
   "CODCOM": 13114,
   "2024": 1,
   "2025": 0,
   "variacion": -100,
   "situación": "Disminución de Casos",
   "COMUNA": "LAS CONDES"
  },
  {
   "delito": "HURTOS",
   "CODCOM": 13114,
   "2024": 1429,
   "2025": 1616,
   "variacion": 13,
   "situación": "Aumento de Casos",
   "COMUNA": "LAS CONDES"
  },
  {
   "delito": "LESIONES",
   "CODCOM": 13114,
   "2024": 287,
   "2025": 278,
   "variacion": -3,
   "situación": "Disminución de Casos",
   "COMUNA": "LAS CONDES"
  },
  {
   "delito": "OTROS ROBOS CON FUERZA",
   "CODCOM": 13114,
   "2024": 90,
   "2025": 68,
   "variacion": -24,
   "situación": "Disminución de Casos",
   "COMUNA": "LAS CONDES"
  },
  {
   "delito": "ROBO CON INTIMIDACIÓN",
   "CODCOM": 13114,
   "2024": 116,
   "2025": 133,
   "variacion": 15,
   "situación": "Aumento de Casos",
   "COMUNA": "LAS CONDES"
  },
  {
   "delito": "ROBO CON VIOLENCIA",
   "CODCOM": 13114,
   "2024": 65,
   "2025": 84,
   "variacion": 29,
   "situación": "Aumento de Casos",
   "COMUNA": "LAS CONDES"
  },
  {
   "delito": "ROBO DE OBJETO DE O DESDE VEHÍCULO",
   "CODCOM": 13114,
   "2024": 496,
   "2025": 386,
   "variacion": -22,
   "situación": "Disminución de Casos",
   "COMUNA": "LAS CONDES"
  },
  {
   "delito": "ROBO DE VEHÍCULO",
   "CODCOM": 13114,
   "2024": 210,
   "2025": 210,
   "variacion": 0,
   "situación": "Sin variación de Casos",
   "COMUNA": "LAS CONDES"
  },
  {
   "delito": "ROBO EN LUGAR HABITADO",
   "CODCOM": 13114,
   "2024": 110,
   "2025": 203,
   "variacion": 85,
   "situación": "Aumento de Casos",
   "COMUNA": "LAS CONDES"
  },
  {
   "delito": "ROBO EN LUGAR NO HABITADO",
   "CODCOM": 13114,
   "2024": 123,
   "2025": 149,
   "variacion": 21,
   "situación": "Aumento de Casos",
   "COMUNA": "LAS CONDES"
  },
  {
   "delito": "ROBO POR SORPRESA",
   "CODCOM": 13114,
   "2024": 206,
   "2025": 322,
   "variacion": 56,
   "situación": "Aumento de Casos",
   "COMUNA": "LAS CONDES"
  },
  {
   "delito": "ROBO VIOLENTO DE VEHÍCULO",
   "CODCOM": 13114,
   "2024": 24,
   "2025": 33,
   "variacion": 38,
   "situación": "Aumento de Casos",
   "COMUNA": "LAS CONDES"
  },
  {
   "delito": "VIOLACIONES",
   "CODCOM": 13114,
   "2024": 10,
   "2025": 8,
   "variacion": -20,
   "situación": "Disminución de Casos",
   "COMUNA": "LAS CONDES"
  }
 ],
 "mensual": [
  {
   "delito": "HOMICIDIOS",
   "CODCOM": 13114,
   "anio": 2024,
   "mes": 1,
   "casos": 0,
   "COMUNA": "LAS CONDES"
  },
  {
   "delito": "HOMICIDIOS",
   "CODCOM": 13114,
   "anio": 2024,
   "mes": 2,
   "casos": 0,
   "COMUNA": "LAS CONDES"
  },
  {
   "delito": "HOMICIDIOS",
   "CODCOM": 13114,
   "anio": 2024,
   "mes": 3,
   "casos": 0,
   "COMUNA": "LAS CONDES"
  },
  {
   "delito": "HOMICIDIOS",
   "CODCOM": 13114,
   "anio": 2024,
   "mes": 4,
   "casos": 0,
   "COMUNA": "LAS CONDES"
  },
  {
   "delito": "HOMICIDIOS",
   "CODCOM": 13114,
   "anio": 2024,
   "mes": 5,
   "casos": 0,
   "COMUNA": "LAS CONDES"
  },
  {
   "delito": "HOMICIDIOS",
   "CODCOM": 13114,
   "anio": 2024,
   "mes": 6,
   "casos": 0,
   "COMUNA": "LAS CONDES"
  },
  {
   "delito": "HOMICIDIOS",
   "CODCOM": 13114,
   "anio": 2024,
   "mes": 7,
   "casos": 0,
   "COMUNA": "LAS CONDES"
  },
  {
   "delito": "HOMICIDIOS",
   "CODCOM": 13114,
   "anio": 2024,
   "mes": 8,
   "casos": 1,
   "COMUNA": "LAS CONDES"
  },
  {
   "delito": "HOMICIDIOS",
   "CODCOM": 13114,
   "anio": 2024,
   "mes": 9,
   "casos": 0,
   "COMUNA": "LAS CONDES"
  },
  {
   "delito": "HOMICIDIOS",
   "CODCOM": 13114,
   "anio": 2024,
   "mes": 10,
   "casos": 0,
   "COMUNA": "LAS CONDES"
  },
  {
   "delito": "HOMICIDIOS",
   "CODCOM": 13114,
   "anio": 2024,
   "mes": 11,
   "casos": 1,
   "COMUNA": "LAS CONDES"
  },
  {
   "delito": "HOMICIDIOS",
   "CODCOM": 13114,
   "anio": 2024,
   "mes": 12,
   "casos": 0,
   "COMUNA": "LAS CONDES"
  },
  {
   "delito": "HOMICIDIOS",
   "CODCOM": 13114,
   "anio": 2025,
   "mes": 1,
   "casos": 0,
   "COMUNA": "LAS CONDES"
  },
  {
   "delito": "HOMICIDIOS",
   "CODCOM": 13114,
   "anio": 2025,
   "mes": 2,
   "casos": 0,
   "COMUNA": "LAS CONDES"
  },
  {
   "delito": "HOMICIDIOS",
   "CODCOM": 13114,
   "anio": 2025,
   "mes": 3,
   "casos": 0,
   "COMUNA": "LAS CONDES"
  },
  {
   "delito": "HOMICIDIOS",
   "CODCOM": 13114,
   "anio": 2025,
   "mes": 4,
   "casos": 0,
   "COMUNA": "LAS CONDES"
  },
  {
   "delito": "HOMICIDIOS",
   "CODCOM": 13114,
   "anio": 2025,
   "mes": 5,
   "casos": 0,
   "COMUNA": "LAS CONDES"
  },
  {
   "delito": "HOMICIDIOS",
   "CODCOM": 13114,
   "anio": 2025,
   "mes": 6,
   "casos": 0,
   "COMUNA": "LAS CONDES"
  },
  {
   "delito": "HOMICIDIOS",
   "CODCOM": 13114,
   "anio": 2025,
   "mes": 7,
   "casos": 0,
   "COMUNA": "LAS CONDES"
  },
  {
   "delito": "HOMICIDIOS",
   "CODCOM": 13114,
   "anio": 2025,
   "mes": 8,
   "casos": 0,
   "COMUNA": "LAS CONDES"
  },
  {
   "delito": "HURTOS",
   "CODCOM": 13114,
   "anio": 2024,
   "mes": 1,
   "casos": 175,
   "COMUNA": "LAS CONDES"
  },
  {
   "delito": "HURTOS",
   "CODCOM": 13114,
   "anio": 2024,
   "mes": 2,
   "casos": 131,
   "COMUNA": "LAS CONDES"
  },
  {
   "delito": "HURTOS",
   "CODCOM": 13114,
   "anio": 2024,
   "mes": 3,
   "casos": 138,
   "COMUNA": "LAS CONDES"
  },
  {
   "delito": "HURTOS",
   "CODCOM": 13114,
   "anio": 2024,
   "mes": 4,
   "casos": 220,
   "COMUNA": "LAS CONDES"
  },
  {
   "delito": "HURTOS",
   "CODCOM": 13114,
   "anio": 2024,
   "mes": 5,
   "casos": 214,
   "COMUNA": "LAS CONDES"
  },
  {
   "delito": "HURTOS",
   "CODCOM": 13114,
   "anio": 2024,
   "mes": 6,
   "casos": 188,
   "COMUNA": "LAS CONDES"
  },
  {
   "delito": "HURTOS",
   "CODCOM": 13114,
   "anio": 2024,
   "mes": 7,
   "casos": 258,
   "COMUNA": "LAS CONDES"
  },
  {
   "delito": "HURTOS",
   "CODCOM": 13114,
   "anio": 2024,
   "mes": 8,
   "casos": 212,
   "COMUNA": "LAS CONDES"
  },
  {
   "delito": "HURTOS",
   "CODCOM": 13114,
   "anio": 2024,
   "mes": 9,
   "casos": 225,
   "COMUNA": "LAS CONDES"
  },
  {
   "delito": "HURTOS",
   "CODCOM": 13114,
   "anio": 2024,
   "mes": 10,
   "casos": 229,
   "COMUNA": "LAS CONDES"
  },
  {
   "delito": "HURTOS",
   "CODCOM": 13114,
   "anio": 2024,
   "mes": 11,
   "casos": 226,
   "COMUNA": "LAS CONDES"
  },
  {
   "delito": "HURTOS",
   "CODCOM": 13114,
   "anio": 2024,
   "mes": 12,
   "casos": 216,
   "COMUNA": "LAS CONDES"
  },
  {
   "delito": "HURTOS",
   "CODCOM": 13114,
   "anio": 2025,
   "mes": 1,
   "casos": 196,
   "COMUNA": "LAS CONDES"
  },
  {
   "delito": "HURTOS",
   "CODCOM": 13114,
   "anio": 2025,
   "mes": 2,
   "casos": 167,
   "COMUNA": "LAS CONDES"
  },
  {
   "delito": "HURTOS",
   "CODCOM": 13114,
   "anio": 2025,
   "mes": 3,
   "casos": 264,
   "COMUNA": "LAS CONDES"
  },
  {
   "delito": "HURTOS",
   "CODCOM": 13114,
   "anio": 2025,
   "mes": 4,
   "casos": 196,
   "COMUNA": "LAS CONDES"
  },
  {
   "delito": "HURTOS",
   "CODCOM": 13114,
   "anio": 2025,
   "mes": 5,
   "casos": 176,
   "COMUNA": "LAS CONDES"
  },
  {
   "delito": "HURTOS",
   "CODCOM": 13114,
   "anio": 2025,
   "mes": 6,
   "casos": 280,
   "COMUNA": "LAS CONDES"
  },
  {
   "delito": "HURTOS",
   "CODCOM": 13114,
   "anio": 2025,
   "mes": 7,
   "casos": 212,
   "COMUNA": "LAS CONDES"
  },
  {
   "delito": "HURTOS",
   "CODCOM": 13114,
   "anio": 2025,
   "mes": 8,
   "casos": 125,
   "COMUNA": "LAS CONDES"
  },
  {
   "delito": "LESIONES",
   "CODCOM": 13114,
   "anio": 2024,
   "mes": 1,
   "casos": 49,
   "COMUNA": "LAS CONDES"
  },
  {
   "delito": "LESIONES",
   "CODCOM": 13114,
   "anio": 2024,
   "mes": 2,
   "casos": 25,
   "COMUNA": "LAS CONDES"
  },
  {
   "delito": "LESIONES",
   "CODCOM": 13114,
   "anio": 2024,
   "mes": 3,
   "casos": 37,
   "COMUNA": "LAS CONDES"
  },
  {
   "delito": "LESIONES",
   "CODCOM": 13114,
   "anio": 2024,
   "mes": 4,
   "casos": 40,
   "COMUNA": "LAS CONDES"
  },
  {
   "delito": "LESIONES",
   "CODCOM": 13114,
   "anio": 2024,
   "mes": 5,
   "casos": 38,
   "COMUNA": "LAS CONDES"
  },
  {
   "delito": "LESIONES",
   "CODCOM": 13114,
   "anio": 2024,
   "mes": 6,
   "casos": 28,
   "COMUNA": "LAS CONDES"
  },
  {
   "delito": "LESIONES",
   "CODCOM": 13114,
   "anio": 2024,
   "mes": 7,
   "casos": 52,
   "COMUNA": "LAS CONDES"
  },
  {
   "delito": "LESIONES",
   "CODCOM": 13114,
   "anio": 2024,
   "mes": 8,
   "casos": 31,
   "COMUNA": "LAS CONDES"
  },
  {
   "delito": "LESIONES",
   "CODCOM": 13114,
   "anio": 2024,
   "mes": 9,
   "casos": 54,
   "COMUNA": "LAS CONDES"
  },
  {
   "delito": "LESIONES",
   "CODCOM": 13114,
   "anio": 2024,
   "mes": 10,
   "casos": 39,
   "COMUNA": "LAS CONDES"
  },
  {
   "delito": "LESIONES",
   "CODCOM": 13114,
   "anio": 2024,
   "mes": 11,
   "casos": 44,
   "COMUNA": "LAS CONDES"
  },
  {
   "delito": "LESIONES",
   "CODCOM": 13114,
   "anio": 2024,
   "mes": 12,
   "casos": 44,
   "COMUNA": "LAS CONDES"
  },
  {
   "delito": "LESIONES",
   "CODCOM": 13114,
   "anio": 2025,
   "mes": 1,
   "casos": 33,
   "COMUNA": "LAS CONDES"
  },
  {
   "delito": "LESIONES",
   "CODCOM": 13114,
   "anio": 2025,
   "mes": 2,
   "casos": 31,
   "COMUNA": "LAS CONDES"
  },
  {
   "delito": "LESIONES",
   "CODCOM": 13114,
   "anio": 2025,
   "mes": 3,
   "casos": 55,
   "COMUNA": "LAS CONDES"
  },
  {
   "delito": "LESIONES",
   "CODCOM": 13114,
   "anio": 2025,
   "mes": 4,
   "casos": 24,
   "COMUNA": "LAS CONDES"
  },
  {
   "delito": "LESIONES",
   "CODCOM": 13114,
   "anio": 2025,
   "mes": 5,
   "casos": 29,
   "COMUNA": "LAS CONDES"
  },
  {
   "delito": "LESIONES",
   "CODCOM": 13114,
   "anio": 2025,
   "mes": 6,
   "casos": 49,
   "COMUNA": "LAS CONDES"
  },
  {
   "delito": "LESIONES",
   "CODCOM": 13114,
   "anio": 2025,
   "mes": 7,
   "casos": 43,
   "COMUNA": "LAS CONDES"
  },
  {
   "delito": "LESIONES",
   "CODCOM": 13114,
   "anio": 2025,
   "mes": 8,
   "casos": 14,
   "COMUNA": "LAS CONDES"
  },
  {
   "delito": "OTROS ROBOS CON FUERZA",
   "CODCOM": 13114,
   "anio": 2024,
   "mes": 1,
   "casos": 15,
   "COMUNA": "LAS CONDES"
  },
  {
   "delito": "OTROS ROBOS CON FUERZA",
   "CODCOM": 13114,
   "anio": 2024,
   "mes": 2,
   "casos": 12,
   "COMUNA": "LAS CONDES"
  },
  {
   "delito": "OTROS ROBOS CON FUERZA",
   "CODCOM": 13114,
   "anio": 2024,
   "mes": 3,
   "casos": 9,
   "COMUNA": "LAS CONDES"
  },
  {
   "delito": "OTROS ROBOS CON FUERZA",
   "CODCOM": 13114,
   "anio": 2024,
   "mes": 4,
   "casos": 17,
   "COMUNA": "LAS CONDES"
  },
  {
   "delito": "OTROS ROBOS CON FUERZA",
   "CODCOM": 13114,
   "anio": 2024,
   "mes": 5,
   "casos": 13,
   "COMUNA": "LAS CONDES"
  },
  {
   "delito": "OTROS ROBOS CON FUERZA",
   "CODCOM": 13114,
   "anio": 2024,
   "mes": 6,
   "casos": 7,
   "COMUNA": "LAS CONDES"
  },
  {
   "delito": "OTROS ROBOS CON FUERZA",
   "CODCOM": 13114,
   "anio": 2024,
   "mes": 7,
   "casos": 13,
   "COMUNA": "LAS CONDES"
  },
  {
   "delito": "OTROS ROBOS CON FUERZA",
   "CODCOM": 13114,
   "anio": 2024,
   "mes": 8,
   "casos": 11,
   "COMUNA": "LAS CONDES"
  },
  {
   "delito": "OTROS ROBOS CON FUERZA",
   "CODCOM": 13114,
   "anio": 2024,
   "mes": 9,
   "casos": 15,
   "COMUNA": "LAS CONDES"
  },
  {
   "delito": "OTROS ROBOS CON FUERZA",
   "CODCOM": 13114,
   "anio": 2024,
   "mes": 10,
   "casos": 17,
   "COMUNA": "LAS CONDES"
  },
  {
   "delito": "OTROS ROBOS CON FUERZA",
   "CODCOM": 13114,
   "anio": 2024,
   "mes": 11,
   "casos": 17,
   "COMUNA": "LAS CONDES"
  },
  {
   "delito": "OTROS ROBOS CON FUERZA",
   "CODCOM": 13114,
   "anio": 2024,
   "mes": 12,
   "casos": 13,
   "COMUNA": "LAS CONDES"
  },
  {
   "delito": "OTROS ROBOS CON FUERZA",
   "CODCOM": 13114,
   "anio": 2025,
   "mes": 1,
   "casos": 12,
   "COMUNA": "LAS CONDES"
  },
  {
   "delito": "OTROS ROBOS CON FUERZA",
   "CODCOM": 13114,
   "anio": 2025,
   "mes": 2,
   "casos": 8,
   "COMUNA": "LAS CONDES"
  },
  {
   "delito": "OTROS ROBOS CON FUERZA",
   "CODCOM": 13114,
   "anio": 2025,
   "mes": 3,
   "casos": 13,
   "COMUNA": "LAS CONDES"
  },
  {
   "delito": "OTROS ROBOS CON FUERZA",
   "CODCOM": 13114,
   "anio": 2025,
   "mes": 4,
   "casos": 6,
   "COMUNA": "LAS CONDES"
  },
  {
   "delito": "OTROS ROBOS CON FUERZA",
   "CODCOM": 13114,
   "anio": 2025,
   "mes": 5,
   "casos": 5,
   "COMUNA": "LAS CONDES"
  },
  {
   "delito": "OTROS ROBOS CON FUERZA",
   "CODCOM": 13114,
   "anio": 2025,
   "mes": 6,
   "casos": 11,
   "COMUNA": "LAS CONDES"
  },
  {
   "delito": "OTROS ROBOS CON FUERZA",
   "CODCOM": 13114,
   "anio": 2025,
   "mes": 7,
   "casos": 9,
   "COMUNA": "LAS CONDES"
  },
  {
   "delito": "OTROS ROBOS CON FUERZA",
   "CODCOM": 13114,
   "anio": 2025,
   "mes": 8,
   "casos": 4,
   "COMUNA": "LAS CONDES"
  },
  {
   "delito": "ROBO CON INTIMIDACIÓN",
   "CODCOM": 13114,
   "anio": 2024,
   "mes": 1,
   "casos": 19,
   "COMUNA": "LAS CONDES"
  },
  {
   "delito": "ROBO CON INTIMIDACIÓN",
   "CODCOM": 13114,
   "anio": 2024,
   "mes": 2,
   "casos": 6,
   "COMUNA": "LAS CONDES"
  },
  {
   "delito": "ROBO CON INTIMIDACIÓN",
   "CODCOM": 13114,
   "anio": 2024,
   "mes": 3,
   "casos": 6,
   "COMUNA": "LAS CONDES"
  },
  {
   "delito": "ROBO CON INTIMIDACIÓN",
   "CODCOM": 13114,
   "anio": 2024,
   "mes": 4,
   "casos": 16,
   "COMUNA": "LAS CONDES"
  },
  {
   "delito": "ROBO CON INTIMIDACIÓN",
   "CODCOM": 13114,
   "anio": 2024,
   "mes": 5,
   "casos": 19,
   "COMUNA": "LAS CONDES"
  },
  {
   "delito": "ROBO CON INTIMIDACIÓN",
   "CODCOM": 13114,
   "anio": 2024,
   "mes": 6,
   "casos": 20,
   "COMUNA": "LAS CONDES"
  },
  {
   "delito": "ROBO CON INTIMIDACIÓN",
   "CODCOM": 13114,
   "anio": 2024,
   "mes": 7,
   "casos": 27,
   "COMUNA": "LAS CONDES"
  },
  {
   "delito": "ROBO CON INTIMIDACIÓN",
   "CODCOM": 13114,
   "anio": 2024,
   "mes": 8,
   "casos": 16,
   "COMUNA": "LAS CONDES"
  },
  {
   "delito": "ROBO CON INTIMIDACIÓN",
   "CODCOM": 13114,
   "anio": 2024,
   "mes": 9,
   "casos": 24,
   "COMUNA": "LAS CONDES"
  },
  {
   "delito": "ROBO CON INTIMIDACIÓN",
   "CODCOM": 13114,
   "anio": 2024,
   "mes": 10,
   "casos": 19,
   "COMUNA": "LAS CONDES"
  },
  {
   "delito": "ROBO CON INTIMIDACIÓN",
   "CODCOM": 13114,
   "anio": 2024,
   "mes": 11,
   "casos": 15,
   "COMUNA": "LAS CONDES"
  },
  {
   "delito": "ROBO CON INTIMIDACIÓN",
   "CODCOM": 13114,
   "anio": 2024,
   "mes": 12,
   "casos": 12,
   "COMUNA": "LAS CONDES"
  },
  {
   "delito": "ROBO CON INTIMIDACIÓN",
   "CODCOM": 13114,
   "anio": 2025,
   "mes": 1,
   "casos": 11,
   "COMUNA": "LAS CONDES"
  },
  {
   "delito": "ROBO CON INTIMIDACIÓN",
   "CODCOM": 13114,
   "anio": 2025,
   "mes": 2,
   "casos": 20,
   "COMUNA": "LAS CONDES"
  },
  {
   "delito": "ROBO CON INTIMIDACIÓN",
   "CODCOM": 13114,
   "anio": 2025,
   "mes": 3,
   "casos": 26,
   "COMUNA": "LAS CONDES"
  },
  {
   "delito": "ROBO CON INTIMIDACIÓN",
   "CODCOM": 13114,
   "anio": 2025,
   "mes": 4,
   "casos": 20,
   "COMUNA": "LAS CONDES"
  },
  {
   "delito": "ROBO CON INTIMIDACIÓN",
   "CODCOM": 13114,
   "anio": 2025,
   "mes": 5,
   "casos": 7,
   "COMUNA": "LAS CONDES"
  },
  {
   "delito": "ROBO CON INTIMIDACIÓN",
   "CODCOM": 13114,
   "anio": 2025,
   "mes": 6,
   "casos": 23,
   "COMUNA": "LAS CONDES"
  },
  {
   "delito": "ROBO CON INTIMIDACIÓN",
   "CODCOM": 13114,
   "anio": 2025,
   "mes": 7,
   "casos": 17,
   "COMUNA": "LAS CONDES"
  },
  {
   "delito": "ROBO CON INTIMIDACIÓN",
   "CODCOM": 13114,
   "anio": 2025,
   "mes": 8,
   "casos": 9,
   "COMUNA": "LAS CONDES"
  },
  {
   "delito": "ROBO CON VIOLENCIA",
   "CODCOM": 13114,
   "anio": 2024,
   "mes": 1,
   "casos": 6,
   "COMUNA": "LAS CONDES"
  },
  {
   "delito": "ROBO CON VIOLENCIA",
   "CODCOM": 13114,
   "anio": 2024,
   "mes": 2,
   "casos": 6,
   "COMUNA": "LAS CONDES"
  },
  {
   "delito": "ROBO CON VIOLENCIA",
   "CODCOM": 13114,
   "anio": 2024,
   "mes": 3,
   "casos": 5,
   "COMUNA": "LAS CONDES"
  },
  {
   "delito": "ROBO CON VIOLENCIA",
   "CODCOM": 13114,
   "anio": 2024,
   "mes": 4,
   "casos": 10,
   "COMUNA": "LAS CONDES"
  },
  {
   "delito": "ROBO CON VIOLENCIA",
   "CODCOM": 13114,
   "anio": 2024,
   "mes": 5,
   "casos": 6,
   "COMUNA": "LAS CONDES"
  },
  {
   "delito": "ROBO CON VIOLENCIA",
   "CODCOM": 13114,
   "anio": 2024,
   "mes": 6,
   "casos": 10,
   "COMUNA": "LAS CONDES"
  },
  {
   "delito": "ROBO CON VIOLENCIA",
   "CODCOM": 13114,
   "anio": 2024,
   "mes": 7,
   "casos": 14,
   "COMUNA": "LAS CONDES"
  },
  {
   "delito": "ROBO CON VIOLENCIA",
   "CODCOM": 13114,
   "anio": 2024,
   "mes": 8,
   "casos": 10,
   "COMUNA": "LAS CONDES"
  },
  {
   "delito": "ROBO CON VIOLENCIA",
   "CODCOM": 13114,
   "anio": 2024,
   "mes": 9,
   "casos": 8,
   "COMUNA": "LAS CONDES"
  },
  {
   "delito": "ROBO CON VIOLENCIA",
   "CODCOM": 13114,
   "anio": 2024,
   "mes": 10,
   "casos": 7,
   "COMUNA": "LAS CONDES"
  },
  {
   "delito": "ROBO CON VIOLENCIA",
   "CODCOM": 13114,
   "anio": 2024,
   "mes": 11,
   "casos": 8,
   "COMUNA": "LAS CONDES"
  },
  {
   "delito": "ROBO CON VIOLENCIA",
   "CODCOM": 13114,
   "anio": 2024,
   "mes": 12,
   "casos": 9,
   "COMUNA": "LAS CONDES"
  },
  {
   "delito": "ROBO CON VIOLENCIA",
   "CODCOM": 13114,
   "anio": 2025,
   "mes": 1,
   "casos": 9,
   "COMUNA": "LAS CONDES"
  },
  {
   "delito": "ROBO CON VIOLENCIA",
   "CODCOM": 13114,
   "anio": 2025,
   "mes": 2,
   "casos": 10,
   "COMUNA": "LAS CONDES"
  },
  {
   "delito": "ROBO CON VIOLENCIA",
   "CODCOM": 13114,
   "anio": 2025,
   "mes": 3,
   "casos": 12,
   "COMUNA": "LAS CONDES"
  },
  {
   "delito": "ROBO CON VIOLENCIA",
   "CODCOM": 13114,
   "anio": 2025,
   "mes": 4,
   "casos": 13,
   "COMUNA": "LAS CONDES"
  },
  {
   "delito": "ROBO CON VIOLENCIA",
   "CODCOM": 13114,
   "anio": 2025,
   "mes": 5,
   "casos": 8,
   "COMUNA": "LAS CONDES"
  },
  {
   "delito": "ROBO CON VIOLENCIA",
   "CODCOM": 13114,
   "anio": 2025,
   "mes": 6,
   "casos": 14,
   "COMUNA": "LAS CONDES"
  },
  {
   "delito": "ROBO CON VIOLENCIA",
   "CODCOM": 13114,
   "anio": 2025,
   "mes": 7,
   "casos": 12,
   "COMUNA": "LAS CONDES"
  },
  {
   "delito": "ROBO CON VIOLENCIA",
   "CODCOM": 13114,
   "anio": 2025,
   "mes": 8,
   "casos": 6,
   "COMUNA": "LAS CONDES"
  },
  {
   "delito": "ROBO DE OBJETO DE O DESDE VEHÍCULO",
   "CODCOM": 13114,
   "anio": 2024,
   "mes": 1,
   "casos": 61,
   "COMUNA": "LAS CONDES"
  },
  {
   "delito": "ROBO DE OBJETO DE O DESDE VEHÍCULO",
   "CODCOM": 13114,
   "anio": 2024,
   "mes": 2,
   "casos": 48,
   "COMUNA": "LAS CONDES"
  },
  {
   "delito": "ROBO DE OBJETO DE O DESDE VEHÍCULO",
   "CODCOM": 13114,
   "anio": 2024,
   "mes": 3,
   "casos": 44,
   "COMUNA": "LAS CONDES"
  },
  {
   "delito": "ROBO DE OBJETO DE O DESDE VEHÍCULO",
   "CODCOM": 13114,
   "anio": 2024,
   "mes": 4,
   "casos": 91,
   "COMUNA": "LAS CONDES"
  },
  {
   "delito": "ROBO DE OBJETO DE O DESDE VEHÍCULO",
   "CODCOM": 13114,
   "anio": 2024,
   "mes": 5,
   "casos": 73,
   "COMUNA": "LAS CONDES"
  },
  {
   "delito": "ROBO DE OBJETO DE O DESDE VEHÍCULO",
   "CODCOM": 13114,
   "anio": 2024,
   "mes": 6,
   "casos": 75,
   "COMUNA": "LAS CONDES"
  },
  {
   "delito": "ROBO DE OBJETO DE O DESDE VEHÍCULO",
   "CODCOM": 13114,
   "anio": 2024,
   "mes": 7,
   "casos": 77,
   "COMUNA": "LAS CONDES"
  },
  {
   "delito": "ROBO DE OBJETO DE O DESDE VEHÍCULO",
   "CODCOM": 13114,
   "anio": 2024,
   "mes": 8,
   "casos": 57,
   "COMUNA": "LAS CONDES"
  },
  {
   "delito": "ROBO DE OBJETO DE O DESDE VEHÍCULO",
   "CODCOM": 13114,
   "anio": 2024,
   "mes": 9,
   "casos": 84,
   "COMUNA": "LAS CONDES"
  },
  {
   "delito": "ROBO DE OBJETO DE O DESDE VEHÍCULO",
   "CODCOM": 13114,
   "anio": 2024,
   "mes": 10,
   "casos": 61,
   "COMUNA": "LAS CONDES"
  },
  {
   "delito": "ROBO DE OBJETO DE O DESDE VEHÍCULO",
   "CODCOM": 13114,
   "anio": 2024,
   "mes": 11,
   "casos": 71,
   "COMUNA": "LAS CONDES"
  },
  {
   "delito": "ROBO DE OBJETO DE O DESDE VEHÍCULO",
   "CODCOM": 13114,
   "anio": 2024,
   "mes": 12,
   "casos": 72,
   "COMUNA": "LAS CONDES"
  },
  {
   "delito": "ROBO DE OBJETO DE O DESDE VEHÍCULO",
   "CODCOM": 13114,
   "anio": 2025,
   "mes": 1,
   "casos": 61,
   "COMUNA": "LAS CONDES"
  },
  {
   "delito": "ROBO DE OBJETO DE O DESDE VEHÍCULO",
   "CODCOM": 13114,
   "anio": 2025,
   "mes": 2,
   "casos": 54,
   "COMUNA": "LAS CONDES"
  },
  {
   "delito": "ROBO DE OBJETO DE O DESDE VEHÍCULO",
   "CODCOM": 13114,
   "anio": 2025,
   "mes": 3,
   "casos": 61,
   "COMUNA": "LAS CONDES"
  },
  {
   "delito": "ROBO DE OBJETO DE O DESDE VEHÍCULO",
   "CODCOM": 13114,
   "anio": 2025,
   "mes": 4,
   "casos": 44,
   "COMUNA": "LAS CONDES"
  },
  {
   "delito": "ROBO DE OBJETO DE O DESDE VEHÍCULO",
   "CODCOM": 13114,
   "anio": 2025,
   "mes": 5,
   "casos": 41,
   "COMUNA": "LAS CONDES"
  },
  {
   "delito": "ROBO DE OBJETO DE O DESDE VEHÍCULO",
   "CODCOM": 13114,
   "anio": 2025,
   "mes": 6,
   "casos": 52,
   "COMUNA": "LAS CONDES"
  },
  {
   "delito": "ROBO DE OBJETO DE O DESDE VEHÍCULO",
   "CODCOM": 13114,
   "anio": 2025,
   "mes": 7,
   "casos": 50,
   "COMUNA": "LAS CONDES"
  },
  {
   "delito": "ROBO DE OBJETO DE O DESDE VEHÍCULO",
   "CODCOM": 13114,
   "anio": 2025,
   "mes": 8,
   "casos": 23,
   "COMUNA": "LAS CONDES"
  },
  {
   "delito": "ROBO DE VEHÍCULO",
   "CODCOM": 13114,
   "anio": 2024,
   "mes": 1,
   "casos": 20,
   "COMUNA": "LAS CONDES"
  },
  {
   "delito": "ROBO DE VEHÍCULO",
   "CODCOM": 13114,
   "anio": 2024,
   "mes": 2,
   "casos": 25,
   "COMUNA": "LAS CONDES"
  },
  {
   "delito": "ROBO DE VEHÍCULO",
   "CODCOM": 13114,
   "anio": 2024,
   "mes": 3,
   "casos": 37,
   "COMUNA": "LAS CONDES"
  },
  {
   "delito": "ROBO DE VEHÍCULO",
   "CODCOM": 13114,
   "anio": 2024,
   "mes": 4,
   "casos": 31,
   "COMUNA": "LAS CONDES"
  },
  {
   "delito": "ROBO DE VEHÍCULO",
   "CODCOM": 13114,
   "anio": 2024,
   "mes": 5,
   "casos": 27,
   "COMUNA": "LAS CONDES"
  },
  {
   "delito": "ROBO DE VEHÍCULO",
   "CODCOM": 13114,
   "anio": 2024,
   "mes": 6,
   "casos": 32,
   "COMUNA": "LAS CONDES"
  },
  {
   "delito": "ROBO DE VEHÍCULO",
   "CODCOM": 13114,
   "anio": 2024,
   "mes": 7,
   "casos": 27,
   "COMUNA": "LAS CONDES"
  },
  {
   "delito": "ROBO DE VEHÍCULO",
   "CODCOM": 13114,
   "anio": 2024,
   "mes": 8,
   "casos": 23,
   "COMUNA": "LAS CONDES"
  },
  {
   "delito": "ROBO DE VEHÍCULO",
   "CODCOM": 13114,
   "anio": 2024,
   "mes": 9,
   "casos": 17,
   "COMUNA": "LAS CONDES"
  },
  {
   "delito": "ROBO DE VEHÍCULO",
   "CODCOM": 13114,
   "anio": 2024,
   "mes": 10,
   "casos": 19,
   "COMUNA": "LAS CONDES"
  },
  {
   "delito": "ROBO DE VEHÍCULO",
   "CODCOM": 13114,
   "anio": 2024,
   "mes": 11,
   "casos": 33,
   "COMUNA": "LAS CONDES"
  },
  {
   "delito": "ROBO DE VEHÍCULO",
   "CODCOM": 13114,
   "anio": 2024,
   "mes": 12,
   "casos": 36,
   "COMUNA": "LAS CONDES"
  },
  {
   "delito": "ROBO DE VEHÍCULO",
   "CODCOM": 13114,
   "anio": 2025,
   "mes": 1,
   "casos": 41,
   "COMUNA": "LAS CONDES"
  },
  {
   "delito": "ROBO DE VEHÍCULO",
   "CODCOM": 13114,
   "anio": 2025,
   "mes": 2,
   "casos": 25,
   "COMUNA": "LAS CONDES"
  },
  {
   "delito": "ROBO DE VEHÍCULO",
   "CODCOM": 13114,
   "anio": 2025,
   "mes": 3,
   "casos": 30,
   "COMUNA": "LAS CONDES"
  },
  {
   "delito": "ROBO DE VEHÍCULO",
   "CODCOM": 13114,
   "anio": 2025,
   "mes": 4,
   "casos": 25,
   "COMUNA": "LAS CONDES"
  },
  {
   "delito": "ROBO DE VEHÍCULO",
   "CODCOM": 13114,
   "anio": 2025,
   "mes": 5,
   "casos": 16,
   "COMUNA": "LAS CONDES"
  },
  {
   "delito": "ROBO DE VEHÍCULO",
   "CODCOM": 13114,
   "anio": 2025,
   "mes": 6,
   "casos": 25,
   "COMUNA": "LAS CONDES"
  },
  {
   "delito": "ROBO DE VEHÍCULO",
   "CODCOM": 13114,
   "anio": 2025,
   "mes": 7,
   "casos": 29,
   "COMUNA": "LAS CONDES"
  },
  {
   "delito": "ROBO DE VEHÍCULO",
   "CODCOM": 13114,
   "anio": 2025,
   "mes": 8,
   "casos": 19,
   "COMUNA": "LAS CONDES"
  },
  {
   "delito": "ROBO EN LUGAR HABITADO",
   "CODCOM": 13114,
   "anio": 2024,
   "mes": 1,
   "casos": 16,
   "COMUNA": "LAS CONDES"
  },
  {
   "delito": "ROBO EN LUGAR HABITADO",
   "CODCOM": 13114,
   "anio": 2024,
   "mes": 2,
   "casos": 13,
   "COMUNA": "LAS CONDES"
  },
  {
   "delito": "ROBO EN LUGAR HABITADO",
   "CODCOM": 13114,
   "anio": 2024,
   "mes": 3,
   "casos": 6,
   "COMUNA": "LAS CONDES"
  },
  {
   "delito": "ROBO EN LUGAR HABITADO",
   "CODCOM": 13114,
   "anio": 2024,
   "mes": 4,
   "casos": 19,
   "COMUNA": "LAS CONDES"
  },
  {
   "delito": "ROBO EN LUGAR HABITADO",
   "CODCOM": 13114,
   "anio": 2024,
   "mes": 5,
   "casos": 17,
   "COMUNA": "LAS CONDES"
  },
  {
   "delito": "ROBO EN LUGAR HABITADO",
   "CODCOM": 13114,
   "anio": 2024,
   "mes": 6,
   "casos": 11,
   "COMUNA": "LAS CONDES"
  },
  {
   "delito": "ROBO EN LUGAR HABITADO",
   "CODCOM": 13114,
   "anio": 2024,
   "mes": 7,
   "casos": 20,
   "COMUNA": "LAS CONDES"
  },
  {
   "delito": "ROBO EN LUGAR HABITADO",
   "CODCOM": 13114,
   "anio": 2024,
   "mes": 8,
   "casos": 18,
   "COMUNA": "LAS CONDES"
  },
  {
   "delito": "ROBO EN LUGAR HABITADO",
   "CODCOM": 13114,
   "anio": 2024,
   "mes": 9,
   "casos": 28,
   "COMUNA": "LAS CONDES"
  },
  {
   "delito": "ROBO EN LUGAR HABITADO",
   "CODCOM": 13114,
   "anio": 2024,
   "mes": 10,
   "casos": 10,
   "COMUNA": "LAS CONDES"
  },
  {
   "delito": "ROBO EN LUGAR HABITADO",
   "CODCOM": 13114,
   "anio": 2024,
   "mes": 11,
   "casos": 11,
   "COMUNA": "LAS CONDES"
  },
  {
   "delito": "ROBO EN LUGAR HABITADO",
   "CODCOM": 13114,
   "anio": 2024,
   "mes": 12,
   "casos": 22,
   "COMUNA": "LAS CONDES"
  },
  {
   "delito": "ROBO EN LUGAR HABITADO",
   "CODCOM": 13114,
   "anio": 2025,
   "mes": 1,
   "casos": 40,
   "COMUNA": "LAS CONDES"
  },
  {
   "delito": "ROBO EN LUGAR HABITADO",
   "CODCOM": 13114,
   "anio": 2025,
   "mes": 2,
   "casos": 30,
   "COMUNA": "LAS CONDES"
  },
  {
   "delito": "ROBO EN LUGAR HABITADO",
   "CODCOM": 13114,
   "anio": 2025,
   "mes": 3,
   "casos": 29,
   "COMUNA": "LAS CONDES"
  },
  {
   "delito": "ROBO EN LUGAR HABITADO",
   "CODCOM": 13114,
   "anio": 2025,
   "mes": 4,
   "casos": 22,
   "COMUNA": "LAS CONDES"
  },
  {
   "delito": "ROBO EN LUGAR HABITADO",
   "CODCOM": 13114,
   "anio": 2025,
   "mes": 5,
   "casos": 17,
   "COMUNA": "LAS CONDES"
  },
  {
   "delito": "ROBO EN LUGAR HABITADO",
   "CODCOM": 13114,
   "anio": 2025,
   "mes": 6,
   "casos": 33,
   "COMUNA": "LAS CONDES"
  },
  {
   "delito": "ROBO EN LUGAR HABITADO",
   "CODCOM": 13114,
   "anio": 2025,
   "mes": 7,
   "casos": 28,
   "COMUNA": "LAS CONDES"
  },
  {
   "delito": "ROBO EN LUGAR HABITADO",
   "CODCOM": 13114,
   "anio": 2025,
   "mes": 8,
   "casos": 4,
   "COMUNA": "LAS CONDES"
  },
  {
   "delito": "ROBO EN LUGAR NO HABITADO",
   "CODCOM": 13114,
   "anio": 2024,
   "mes": 1,
   "casos": 18,
   "COMUNA": "LAS CONDES"
  },
  {
   "delito": "ROBO EN LUGAR NO HABITADO",
   "CODCOM": 13114,
   "anio": 2024,
   "mes": 2,
   "casos": 7,
   "COMUNA": "LAS CONDES"
  },
  {
   "delito": "ROBO EN LUGAR NO HABITADO",
   "CODCOM": 13114,
   "anio": 2024,
   "mes": 3,
   "casos": 18,
   "COMUNA": "LAS CONDES"
  },
  {
   "delito": "ROBO EN LUGAR NO HABITADO",
   "CODCOM": 13114,
   "anio": 2024,
   "mes": 4,
   "casos": 23,
   "COMUNA": "LAS CONDES"
  },
  {
   "delito": "ROBO EN LUGAR NO HABITADO",
   "CODCOM": 13114,
   "anio": 2024,
   "mes": 5,
   "casos": 15,
   "COMUNA": "LAS CONDES"
  },
  {
   "delito": "ROBO EN LUGAR NO HABITADO",
   "CODCOM": 13114,
   "anio": 2024,
   "mes": 6,
   "casos": 14,
   "COMUNA": "LAS CONDES"
  },
  {
   "delito": "ROBO EN LUGAR NO HABITADO",
   "CODCOM": 13114,
   "anio": 2024,
   "mes": 7,
   "casos": 19,
   "COMUNA": "LAS CONDES"
  },
  {
   "delito": "ROBO EN LUGAR NO HABITADO",
   "CODCOM": 13114,
   "anio": 2024,
   "mes": 8,
   "casos": 15,
   "COMUNA": "LAS CONDES"
  },
  {
   "delito": "ROBO EN LUGAR NO HABITADO",
   "CODCOM": 13114,
   "anio": 2024,
   "mes": 9,
   "casos": 29,
   "COMUNA": "LAS CONDES"
  },
  {
   "delito": "ROBO EN LUGAR NO HABITADO",
   "CODCOM": 13114,
   "anio": 2024,
   "mes": 10,
   "casos": 24,
   "COMUNA": "LAS CONDES"
  },
  {
   "delito": "ROBO EN LUGAR NO HABITADO",
   "CODCOM": 13114,
   "anio": 2024,
   "mes": 11,
   "casos": 15,
   "COMUNA": "LAS CONDES"
  },
  {
   "delito": "ROBO EN LUGAR NO HABITADO",
   "CODCOM": 13114,
   "anio": 2024,
   "mes": 12,
   "casos": 18,
   "COMUNA": "LAS CONDES"
  },
  {
   "delito": "ROBO EN LUGAR NO HABITADO",
   "CODCOM": 13114,
   "anio": 2025,
   "mes": 1,
   "casos": 32,
   "COMUNA": "LAS CONDES"
  },
  {
   "delito": "ROBO EN LUGAR NO HABITADO",
   "CODCOM": 13114,
   "anio": 2025,
   "mes": 2,
   "casos": 24,
   "COMUNA": "LAS CONDES"
  },
  {
   "delito": "ROBO EN LUGAR NO HABITADO",
   "CODCOM": 13114,
   "anio": 2025,
   "mes": 3,
   "casos": 11,
   "COMUNA": "LAS CONDES"
  },
  {
   "delito": "ROBO EN LUGAR NO HABITADO",
   "CODCOM": 13114,
   "anio": 2025,
   "mes": 4,
   "casos": 20,
   "COMUNA": "LAS CONDES"
  },
  {
   "delito": "ROBO EN LUGAR NO HABITADO",
   "CODCOM": 13114,
   "anio": 2025,
   "mes": 5,
   "casos": 13,
   "COMUNA": "LAS CONDES"
  },
  {
   "delito": "ROBO EN LUGAR NO HABITADO",
   "CODCOM": 13114,
   "anio": 2025,
   "mes": 6,
   "casos": 19,
   "COMUNA": "LAS CONDES"
  },
  {
   "delito": "ROBO EN LUGAR NO HABITADO",
   "CODCOM": 13114,
   "anio": 2025,
   "mes": 7,
   "casos": 21,
   "COMUNA": "LAS CONDES"
  },
  {
   "delito": "ROBO EN LUGAR NO HABITADO",
   "CODCOM": 13114,
   "anio": 2025,
   "mes": 8,
   "casos": 9,
   "COMUNA": "LAS CONDES"
  },
  {
   "delito": "ROBO POR SORPRESA",
   "CODCOM": 13114,
   "anio": 2024,
   "mes": 1,
   "casos": 33,
   "COMUNA": "LAS CONDES"
  },
  {
   "delito": "ROBO POR SORPRESA",
   "CODCOM": 13114,
   "anio": 2024,
   "mes": 2,
   "casos": 13,
   "COMUNA": "LAS CONDES"
  },
  {
   "delito": "ROBO POR SORPRESA",
   "CODCOM": 13114,
   "anio": 2024,
   "mes": 3,
   "casos": 27,
   "COMUNA": "LAS CONDES"
  },
  {
   "delito": "ROBO POR SORPRESA",
   "CODCOM": 13114,
   "anio": 2024,
   "mes": 4,
   "casos": 27,
   "COMUNA": "LAS CONDES"
  },
  {
   "delito": "ROBO POR SORPRESA",
   "CODCOM": 13114,
   "anio": 2024,
   "mes": 5,
   "casos": 25,
   "COMUNA": "LAS CONDES"
  },
  {
   "delito": "ROBO POR SORPRESA",
   "CODCOM": 13114,
   "anio": 2024,
   "mes": 6,
   "casos": 33,
   "COMUNA": "LAS CONDES"
  },
  {
   "delito": "ROBO POR SORPRESA",
   "CODCOM": 13114,
   "anio": 2024,
   "mes": 7,
   "casos": 31,
   "COMUNA": "LAS CONDES"
  },
  {
   "delito": "ROBO POR SORPRESA",
   "CODCOM": 13114,
   "anio": 2024,
   "mes": 8,
   "casos": 29,
   "COMUNA": "LAS CONDES"
  },
  {
   "delito": "ROBO POR SORPRESA",
   "CODCOM": 13114,
   "anio": 2024,
   "mes": 9,
   "casos": 32,
   "COMUNA": "LAS CONDES"
  },
  {
   "delito": "ROBO POR SORPRESA",
   "CODCOM": 13114,
   "anio": 2024,
   "mes": 10,
   "casos": 25,
   "COMUNA": "LAS CONDES"
  },
  {
   "delito": "ROBO POR SORPRESA",
   "CODCOM": 13114,
   "anio": 2024,
   "mes": 11,
   "casos": 25,
   "COMUNA": "LAS CONDES"
  },
  {
   "delito": "ROBO POR SORPRESA",
   "CODCOM": 13114,
   "anio": 2024,
   "mes": 12,
   "casos": 43,
   "COMUNA": "LAS CONDES"
  },
  {
   "delito": "ROBO POR SORPRESA",
   "CODCOM": 13114,
   "anio": 2025,
   "mes": 1,
   "casos": 44,
   "COMUNA": "LAS CONDES"
  },
  {
   "delito": "ROBO POR SORPRESA",
   "CODCOM": 13114,
   "anio": 2025,
   "mes": 2,
   "casos": 40,
   "COMUNA": "LAS CONDES"
  },
  {
   "delito": "ROBO POR SORPRESA",
   "CODCOM": 13114,
   "anio": 2025,
   "mes": 3,
   "casos": 36,
   "COMUNA": "LAS CONDES"
  },
  {
   "delito": "ROBO POR SORPRESA",
   "CODCOM": 13114,
   "anio": 2025,
   "mes": 4,
   "casos": 29,
   "COMUNA": "LAS CONDES"
  },
  {
   "delito": "ROBO POR SORPRESA",
   "CODCOM": 13114,
   "anio": 2025,
   "mes": 5,
   "casos": 52,
   "COMUNA": "LAS CONDES"
  },
  {
   "delito": "ROBO POR SORPRESA",
   "CODCOM": 13114,
   "anio": 2025,
   "mes": 6,
   "casos": 59,
   "COMUNA": "LAS CONDES"
  },
  {
   "delito": "ROBO POR SORPRESA",
   "CODCOM": 13114,
   "anio": 2025,
   "mes": 7,
   "casos": 42,
   "COMUNA": "LAS CONDES"
  },
  {
   "delito": "ROBO POR SORPRESA",
   "CODCOM": 13114,
   "anio": 2025,
   "mes": 8,
   "casos": 20,
   "COMUNA": "LAS CONDES"
  },
  {
   "delito": "ROBO VIOLENTO DE VEHÍCULO",
   "CODCOM": 13114,
   "anio": 2024,
   "mes": 1,
   "casos": 3,
   "COMUNA": "LAS CONDES"
  },
  {
   "delito": "ROBO VIOLENTO DE VEHÍCULO",
   "CODCOM": 13114,
   "anio": 2024,
   "mes": 2,
   "casos": 4,
   "COMUNA": "LAS CONDES"
  },
  {
   "delito": "ROBO VIOLENTO DE VEHÍCULO",
   "CODCOM": 13114,
   "anio": 2024,
   "mes": 3,
   "casos": 1,
   "COMUNA": "LAS CONDES"
  },
  {
   "delito": "ROBO VIOLENTO DE VEHÍCULO",
   "CODCOM": 13114,
   "anio": 2024,
   "mes": 4,
   "casos": 3,
   "COMUNA": "LAS CONDES"
  },
  {
   "delito": "ROBO VIOLENTO DE VEHÍCULO",
   "CODCOM": 13114,
   "anio": 2024,
   "mes": 5,
   "casos": 3,
   "COMUNA": "LAS CONDES"
  },
  {
   "delito": "ROBO VIOLENTO DE VEHÍCULO",
   "CODCOM": 13114,
   "anio": 2024,
   "mes": 6,
   "casos": 2,
   "COMUNA": "LAS CONDES"
  },
  {
   "delito": "ROBO VIOLENTO DE VEHÍCULO",
   "CODCOM": 13114,
   "anio": 2024,
   "mes": 7,
   "casos": 7,
   "COMUNA": "LAS CONDES"
  },
  {
   "delito": "ROBO VIOLENTO DE VEHÍCULO",
   "CODCOM": 13114,
   "anio": 2024,
   "mes": 8,
   "casos": 1,
   "COMUNA": "LAS CONDES"
  },
  {
   "delito": "ROBO VIOLENTO DE VEHÍCULO",
   "CODCOM": 13114,
   "anio": 2024,
   "mes": 9,
   "casos": 5,
   "COMUNA": "LAS CONDES"
  },
  {
   "delito": "ROBO VIOLENTO DE VEHÍCULO",
   "CODCOM": 13114,
   "anio": 2024,
   "mes": 10,
   "casos": 4,
   "COMUNA": "LAS CONDES"
  },
  {
   "delito": "ROBO VIOLENTO DE VEHÍCULO",
   "CODCOM": 13114,
   "anio": 2024,
   "mes": 11,
   "casos": 4,
   "COMUNA": "LAS CONDES"
  },
  {
   "delito": "ROBO VIOLENTO DE VEHÍCULO",
   "CODCOM": 13114,
   "anio": 2024,
   "mes": 12,
   "casos": 3,
   "COMUNA": "LAS CONDES"
  },
  {
   "delito": "ROBO VIOLENTO DE VEHÍCULO",
   "CODCOM": 13114,
   "anio": 2025,
   "mes": 1,
   "casos": 8,
   "COMUNA": "LAS CONDES"
  },
  {
   "delito": "ROBO VIOLENTO DE VEHÍCULO",
   "CODCOM": 13114,
   "anio": 2025,
   "mes": 2,
   "casos": 8,
   "COMUNA": "LAS CONDES"
  },
  {
   "delito": "ROBO VIOLENTO DE VEHÍCULO",
   "CODCOM": 13114,
   "anio": 2025,
   "mes": 3,
   "casos": 2,
   "COMUNA": "LAS CONDES"
  },
  {
   "delito": "ROBO VIOLENTO DE VEHÍCULO",
   "CODCOM": 13114,
   "anio": 2025,
   "mes": 4,
   "casos": 2,
   "COMUNA": "LAS CONDES"
  },
  {
   "delito": "ROBO VIOLENTO DE VEHÍCULO",
   "CODCOM": 13114,
   "anio": 2025,
   "mes": 5,
   "casos": 4,
   "COMUNA": "LAS CONDES"
  },
  {
   "delito": "ROBO VIOLENTO DE VEHÍCULO",
   "CODCOM": 13114,
   "anio": 2025,
   "mes": 6,
   "casos": 5,
   "COMUNA": "LAS CONDES"
  },
  {
   "delito": "ROBO VIOLENTO DE VEHÍCULO",
   "CODCOM": 13114,
   "anio": 2025,
   "mes": 7,
   "casos": 2,
   "COMUNA": "LAS CONDES"
  },
  {
   "delito": "ROBO VIOLENTO DE VEHÍCULO",
   "CODCOM": 13114,
   "anio": 2025,
   "mes": 8,
   "casos": 2,
   "COMUNA": "LAS CONDES"
  },
  {
   "delito": "VIOLACIONES",
   "CODCOM": 13114,
   "anio": 2024,
   "mes": 1,
   "casos": 1,
   "COMUNA": "LAS CONDES"
  },
  {
   "delito": "VIOLACIONES",
   "CODCOM": 13114,
   "anio": 2024,
   "mes": 2,
   "casos": 0,
   "COMUNA": "LAS CONDES"
  },
  {
   "delito": "VIOLACIONES",
   "CODCOM": 13114,
   "anio": 2024,
   "mes": 3,
   "casos": 2,
   "COMUNA": "LAS CONDES"
  },
  {
   "delito": "VIOLACIONES",
   "CODCOM": 13114,
   "anio": 2024,
   "mes": 4,
   "casos": 3,
   "COMUNA": "LAS CONDES"
  },
  {
   "delito": "VIOLACIONES",
   "CODCOM": 13114,
   "anio": 2024,
   "mes": 5,
   "casos": 1,
   "COMUNA": "LAS CONDES"
  },
  {
   "delito": "VIOLACIONES",
   "CODCOM": 13114,
   "anio": 2024,
   "mes": 6,
   "casos": 2,
   "COMUNA": "LAS CONDES"
  },
  {
   "delito": "VIOLACIONES",
   "CODCOM": 13114,
   "anio": 2024,
   "mes": 7,
   "casos": 1,
   "COMUNA": "LAS CONDES"
  },
  {
   "delito": "VIOLACIONES",
   "CODCOM": 13114,
   "anio": 2024,
   "mes": 8,
   "casos": 0,
   "COMUNA": "LAS CONDES"
  },
  {
   "delito": "VIOLACIONES",
   "CODCOM": 13114,
   "anio": 2024,
   "mes": 9,
   "casos": 2,
   "COMUNA": "LAS CONDES"
  },
  {
   "delito": "VIOLACIONES",
   "CODCOM": 13114,
   "anio": 2024,
   "mes": 10,
   "casos": 1,
   "COMUNA": "LAS CONDES"
  },
  {
   "delito": "VIOLACIONES",
   "CODCOM": 13114,
   "anio": 2024,
   "mes": 11,
   "casos": 2,
   "COMUNA": "LAS CONDES"
  },
  {
   "delito": "VIOLACIONES",
   "CODCOM": 13114,
   "anio": 2024,
   "mes": 12,
   "casos": 0,
   "COMUNA": "LAS CONDES"
  },
  {
   "delito": "VIOLACIONES",
   "CODCOM": 13114,
   "anio": 2025,
   "mes": 1,
   "casos": 2,
   "COMUNA": "LAS CONDES"
  },
  {
   "delito": "VIOLACIONES",
   "CODCOM": 13114,
   "anio": 2025,
   "mes": 2,
   "casos": 0,
   "COMUNA": "LAS CONDES"
  },
  {
   "delito": "VIOLACIONES",
   "CODCOM": 13114,
   "anio": 2025,
   "mes": 3,
   "casos": 4,
   "COMUNA": "LAS CONDES"
  },
  {
   "delito": "VIOLACIONES",
   "CODCOM": 13114,
   "anio": 2025,
   "mes": 4,
   "casos": 2,
   "COMUNA": "LAS CONDES"
  },
  {
   "delito": "VIOLACIONES",
   "CODCOM": 13114,
   "anio": 2025,
   "mes": 5,
   "casos": 0,
   "COMUNA": "LAS CONDES"
  },
  {
   "delito": "VIOLACIONES",
   "CODCOM": 13114,
   "anio": 2025,
   "mes": 6,
   "casos": 0,
   "COMUNA": "LAS CONDES"
  },
  {
   "delito": "VIOLACIONES",
   "CODCOM": 13114,
   "anio": 2025,
   "mes": 7,
   "casos": 0,
   "COMUNA": "LAS CONDES"
  },
  {
   "delito": "VIOLACIONES",
   "CODCOM": 13114,
   "anio": 2025,
   "mes": 8,
   "casos": 0,
   "COMUNA": "LAS CONDES"
  }
 ],
 "info": [
  {
   "informacion": "Casos",
   "CODCOM": 13114,
   "delito": "HOMICIDIOS",
   "2024": 1,
   "2025": 0,
   "COMUNA": "LAS CONDES"
  },
  {
   "informacion": "Casos",
   "CODCOM": 13114,
   "delito": "HURTOS",
   "2024": 1429,
   "2025": 1616,
   "COMUNA": "LAS CONDES"
  },
  {
   "informacion": "Casos",
   "CODCOM": 13114,
   "delito": "LESIONES",
   "2024": 287,
   "2025": 278,
   "COMUNA": "LAS CONDES"
  },
  {
   "informacion": "Casos",
   "CODCOM": 13114,
   "delito": "OTROS ROBOS CON FUERZA",
   "2024": 90,
   "2025": 68,
   "COMUNA": "LAS CONDES"
  },
  {
   "informacion": "Casos",
   "CODCOM": 13114,
   "delito": "ROBO CON INTIMIDACIÓN",
   "2024": 116,
   "2025": 133,
   "COMUNA": "LAS CONDES"
  },
  {
   "informacion": "Casos",
   "CODCOM": 13114,
   "delito": "ROBO CON VIOLENCIA",
   "2024": 65,
   "2025": 84,
   "COMUNA": "LAS CONDES"
  },
  {
   "informacion": "Casos",
   "CODCOM": 13114,
   "delito": "ROBO DE OBJETO DE O DESDE VEHÍCULO",
   "2024": 496,
   "2025": 386,
   "COMUNA": "LAS CONDES"
  },
  {
   "informacion": "Casos",
   "CODCOM": 13114,
   "delito": "ROBO DE VEHÍCULO",
   "2024": 210,
   "2025": 210,
   "COMUNA": "LAS CONDES"
  },
  {
   "informacion": "Casos",
   "CODCOM": 13114,
   "delito": "ROBO EN LUGAR HABITADO",
   "2024": 110,
   "2025": 203,
   "COMUNA": "LAS CONDES"
  },
  {
   "informacion": "Casos",
   "CODCOM": 13114,
   "delito": "ROBO EN LUGAR NO HABITADO",
   "2024": 123,
   "2025": 149,
   "COMUNA": "LAS CONDES"
  },
  {
   "informacion": "Casos",
   "CODCOM": 13114,
   "delito": "ROBO POR SORPRESA",
   "2024": 206,
   "2025": 322,
   "COMUNA": "LAS CONDES"
  },
  {
   "informacion": "Casos",
   "CODCOM": 13114,
   "delito": "ROBO VIOLENTO DE VEHÍCULO",
   "2024": 24,
   "2025": 33,
   "COMUNA": "LAS CONDES"
  },
  {
   "informacion": "Casos",
   "CODCOM": 13114,
   "delito": "VIOLACIONES",
   "2024": 10,
   "2025": 8,
   "COMUNA": "LAS CONDES"
  },
  {
   "informacion": "Detenciones",
   "CODCOM": 13114,
   "delito": "HOMICIDIOS",
   "2024": 1,
   "2025": 0,
   "COMUNA": "LAS CONDES"
  },
  {
   "informacion": "Detenciones",
   "CODCOM": 13114,
   "delito": "HURTOS",
   "2024": 594,
   "2025": 574,
   "COMUNA": "LAS CONDES"
  },
  {
   "informacion": "Detenciones",
   "CODCOM": 13114,
   "delito": "LESIONES",
   "2024": 53,
   "2025": 59,
   "COMUNA": "LAS CONDES"
  },
  {
   "informacion": "Detenciones",
   "CODCOM": 13114,
   "delito": "OTROS ROBOS CON FUERZA",
   "2024": 13,
   "2025": 8,
   "COMUNA": "LAS CONDES"
  },
  {
   "informacion": "Detenciones",
   "CODCOM": 13114,
   "delito": "ROBO CON INTIMIDACIÓN",
   "2024": 16,
   "2025": 11,
   "COMUNA": "LAS CONDES"
  },
  {
   "informacion": "Detenciones",
   "CODCOM": 13114,
   "delito": "ROBO CON VIOLENCIA",
   "2024": 12,
   "2025": 10,
   "COMUNA": "LAS CONDES"
  },
  {
   "informacion": "Detenciones",
   "CODCOM": 13114,
   "delito": "ROBO DE OBJETO DE O DESDE VEHÍCULO",
   "2024": 3,
   "2025": 2,
   "COMUNA": "LAS CONDES"
  },
  {
   "informacion": "Detenciones",
   "CODCOM": 13114,
   "delito": "ROBO DE VEHÍCULO",
   "2024": 2,
   "2025": 2,
   "COMUNA": "LAS CONDES"
  },
  {
   "informacion": "Detenciones",
   "CODCOM": 13114,
   "delito": "ROBO EN LUGAR HABITADO",
   "2024": 1,
   "2025": 13,
   "COMUNA": "LAS CONDES"
  },
  {
   "informacion": "Detenciones",
   "CODCOM": 13114,
   "delito": "ROBO EN LUGAR NO HABITADO",
   "2024": 12,
   "2025": 16,
   "COMUNA": "LAS CONDES"
  },
  {
   "informacion": "Detenciones",
   "CODCOM": 13114,
   "delito": "ROBO POR SORPRESA",
   "2024": 14,
   "2025": 15,
   "COMUNA": "LAS CONDES"
  },
  {
   "informacion": "Detenciones",
   "CODCOM": 13114,
   "delito": "ROBO VIOLENTO DE VEHÍCULO",
   "2024": 2,
   "2025": 2,
   "COMUNA": "LAS CONDES"
  },
  {
   "informacion": "Detenciones",
   "CODCOM": 13114,
   "delito": "VIOLACIONES",
   "2024": 2,
   "2025": 0,
   "COMUNA": "LAS CONDES"
  },
  {
   "informacion": "Detenidos",
   "CODCOM": 13114,
   "delito": "HOMICIDIOS",
   "2024": 1,
   "2025": 0,
   "COMUNA": "LAS CONDES"
  },
  {
   "informacion": "Detenidos",
   "CODCOM": 13114,
   "delito": "HURTOS",
   "2024": 625,
   "2025": 617,
   "COMUNA": "LAS CONDES"
  },
  {
   "informacion": "Detenidos",
   "CODCOM": 13114,
   "delito": "LESIONES",
   "2024": 70,
   "2025": 91,
   "COMUNA": "LAS CONDES"
  },
  {
   "informacion": "Detenidos",
   "CODCOM": 13114,
   "delito": "OTROS ROBOS CON FUERZA",
   "2024": 16,
   "2025": 12,
   "COMUNA": "LAS CONDES"
  },
  {
   "informacion": "Detenidos",
   "CODCOM": 13114,
   "delito": "ROBO CON INTIMIDACIÓN",
   "2024": 31,
   "2025": 24,
   "COMUNA": "LAS CONDES"
  },
  {
   "informacion": "Detenidos",
   "CODCOM": 13114,
   "delito": "ROBO CON VIOLENCIA",
   "2024": 29,
   "2025": 25,
   "COMUNA": "LAS CONDES"
  },
  {
   "informacion": "Detenidos",
   "CODCOM": 13114,
   "delito": "ROBO DE OBJETO DE O DESDE VEHÍCULO",
   "2024": 5,
   "2025": 4,
   "COMUNA": "LAS CONDES"
  },
  {
   "informacion": "Detenidos",
   "CODCOM": 13114,
   "delito": "ROBO DE VEHÍCULO",
   "2024": 3,
   "2025": 2,
   "COMUNA": "LAS CONDES"
  },
  {
   "informacion": "Detenidos",
   "CODCOM": 13114,
   "delito": "ROBO EN LUGAR HABITADO",
   "2024": 1,
   "2025": 24,
   "COMUNA": "LAS CONDES"
  },
  {
   "informacion": "Detenidos",
   "CODCOM": 13114,
   "delito": "ROBO EN LUGAR NO HABITADO",
   "2024": 23,
   "2025": 18,
   "COMUNA": "LAS CONDES"
  },
  {
   "informacion": "Detenidos",
   "CODCOM": 13114,
   "delito": "ROBO POR SORPRESA",
   "2024": 20,
   "2025": 19,
   "COMUNA": "LAS CONDES"
  },
  {
   "informacion": "Detenidos",
   "CODCOM": 13114,
   "delito": "ROBO VIOLENTO DE VEHÍCULO",
   "2024": 4,
   "2025": 4,
   "COMUNA": "LAS CONDES"
  },
  {
   "informacion": "Detenidos",
   "CODCOM": 13114,
   "delito": "VIOLACIONES",
   "2024": 2,
   "2025": 0,
   "COMUNA": "LAS CONDES"
  }
 ],
 "meta": {
  "semana_id": "SEMANA 33/2025 (del 11/08/2025 al 17/08/2025)",
  "region": "Metropolitana"
 }
}